{
  "id": "womens-dress-cocktail",
  "handle": "womens-dress-cocktail",
  "sku": "JC1340",
  "asin": "B0FGJ744VP",
  "title": "Womens Dress Cocktail",
  "title_original": "Clothfun Tiered Tulle Short Homecoming Dresses 2025 for Teens Lace Applique Sweet 16 Prom Cocktail Dress CYN021",
  "brand": "Visit the Clothfun Store",
  "price": 94.96,
  "social_proof": {
    "bought_past_month": 124,
    "text": "124+ bought in the past month"
  },
  "images": [
    "https://m.media-amazon.com/images/I/61DWMEm-oaL._SL1500_.jpg",
    "https://m.media-amazon.com/images/I/617tvwtwMnL._SL1500_.jpg",
    "https://m.media-amazon.com/images/I/61peYm1Q-RL._SL1500_.jpg",
    "https://m.media-amazon.com/images/I/617iRRTTNOL._SL1500_.jpg",
    "https://m.media-amazon.com/images/I/612OYlbShuL._SL1500_.jpg",
    "https://m.media-amazon.com/images/I/61HGSyfIoTL._SL1500_.jpg",
    "https://m.media-amazon.com/images/I/61c3n934J2L._SL1500_.jpg",
    "https://m.media-amazon.com/images/I/71tKdkC6qaL._SL1500_.jpg",
    "https://m.media-amazon.com/images/I/61Uwx1afQiL._SL1500_.jpg",
    "https://m.media-amazon.com/images/I/61rL6vrGQXL._SL1500_.jpg",
    "https://m.media-amazon.com/images/I/71cMdetxX5L._SL1500_.jpg",
    "https://m.media-amazon.com/images/I/71CDhJlZRvL._SL1500_.jpg",
    "https://m.media-amazon.com/images/I/71IBCMdSXaL._SL1500_.jpg",
    "https://m.media-amazon.com/images/I/61XDZMwfPLL._SL1500_.jpg",
    "https://m.media-amazon.com/images/I/61XMVIYiEVL._SL1500_.jpg",
    "https://m.media-amazon.com/images/I/71I5l0BNRBL._SL1500_.jpg",
    "https://m.media-amazon.com/images/I/71P4KtckE4L._SL1500_.jpg",
    "https://m.media-amazon.com/images/I/61IoX2nZexL._SL1500_.jpg",
    "https://m.media-amazon.com/images/I/61birFuLt0L._SL1500_.jpg",
    "https://m.media-amazon.com/images/I/71QmlLOhf3L._SL1500_.jpg",
    "https://m.media-amazon.com/images/I/61wUqxxA+eL._SL1500_.jpg",
    "https://m.media-amazon.com/images/I/61SKYwzsSpL._SL1500_.jpg",
    "https://m.media-amazon.com/images/I/71CvGS0UPBL._SL1500_.jpg",
    "https://m.media-amazon.com/images/I/61aiWUAi7kL._SL1500_.jpg",
    "https://m.media-amazon.com/images/I/61bZ5vGe8TL._SL1500_.jpg",
    "https://m.media-amazon.com/images/I/615H9MtRSCL._SL1500_.jpg",
    "https://m.media-amazon.com/images/I/718nP2GsRoL._SL1500_.jpg",
    "https://m.media-amazon.com/images/I/61yJWgQSq0L._SL1500_.jpg",
    "https://m.media-amazon.com/images/I/61QkDNsdF2L._SL1500_.jpg",
    "https://m.media-amazon.com/images/I/616R42slmRL._SL1500_.jpg",
    "https://m.media-amazon.com/images/I/71LYIqO5n2L._SL1500_.jpg",
    "https://m.media-amazon.com/images/I/71nIrNzRpsL._SL1500_.jpg",
    "https://m.media-amazon.com/images/I/71Dcjg1D3OL._SL1500_.jpg",
    "https://m.media-amazon.com/images/I/61s1Y0PNlXL._SL1500_.jpg"
  ],
  "gallery_images": [
    "https://m.media-amazon.com/images/I/61DWMEm-oaL._SL1500_.jpg",
    "https://m.media-amazon.com/images/I/617tvwtwMnL._SL1500_.jpg",
    "https://m.media-amazon.com/images/I/61peYm1Q-RL._SL1500_.jpg",
    "https://m.media-amazon.com/images/I/617iRRTTNOL._SL1500_.jpg",
    "https://m.media-amazon.com/images/I/612OYlbShuL._SL1500_.jpg",
    "https://m.media-amazon.com/images/I/61HGSyfIoTL._SL1500_.jpg",
    "https://m.media-amazon.com/images/I/61c3n934J2L._SL1500_.jpg",
    "https://m.media-amazon.com/images/I/71tKdkC6qaL._SL1500_.jpg",
    "https://m.media-amazon.com/images/I/61Uwx1afQiL._SL1500_.jpg",
    "https://m.media-amazon.com/images/I/61rL6vrGQXL._SL1500_.jpg",
    "https://m.media-amazon.com/images/I/71cMdetxX5L._SL1500_.jpg",
    "https://m.media-amazon.com/images/I/71CDhJlZRvL._SL1500_.jpg",
    "https://m.media-amazon.com/images/I/71IBCMdSXaL._SL1500_.jpg",
    "https://m.media-amazon.com/images/I/61XDZMwfPLL._SL1500_.jpg",
    "https://m.media-amazon.com/images/I/61XMVIYiEVL._SL1500_.jpg",
    "https://m.media-amazon.com/images/I/71I5l0BNRBL._SL1500_.jpg",
    "https://m.media-amazon.com/images/I/71P4KtckE4L._SL1500_.jpg",
    "https://m.media-amazon.com/images/I/61IoX2nZexL._SL1500_.jpg",
    "https://m.media-amazon.com/images/I/61birFuLt0L._SL1500_.jpg",
    "https://m.media-amazon.com/images/I/71QmlLOhf3L._SL1500_.jpg",
    "https://m.media-amazon.com/images/I/61wUqxxA+eL._SL1500_.jpg",
    "https://m.media-amazon.com/images/I/61SKYwzsSpL._SL1500_.jpg",
    "https://m.media-amazon.com/images/I/71CvGS0UPBL._SL1500_.jpg",
    "https://m.media-amazon.com/images/I/61aiWUAi7kL._SL1500_.jpg",
    "https://m.media-amazon.com/images/I/61bZ5vGe8TL._SL1500_.jpg",
    "https://m.media-amazon.com/images/I/615H9MtRSCL._SL1500_.jpg",
    "https://m.media-amazon.com/images/I/718nP2GsRoL._SL1500_.jpg",
    "https://m.media-amazon.com/images/I/61yJWgQSq0L._SL1500_.jpg",
    "https://m.media-amazon.com/images/I/61QkDNsdF2L._SL1500_.jpg",
    "https://m.media-amazon.com/images/I/616R42slmRL._SL1500_.jpg",
    "https://m.media-amazon.com/images/I/71LYIqO5n2L._SL1500_.jpg",
    "https://m.media-amazon.com/images/I/71nIrNzRpsL._SL1500_.jpg",
    "https://m.media-amazon.com/images/I/71Dcjg1D3OL._SL1500_.jpg",
    "https://m.media-amazon.com/images/I/61s1Y0PNlXL._SL1500_.jpg"
  ],
  "aplus_images": [],
  "description_images": [],
  "bullets": [],
  "specs": {
    "Item model number ‏": "‎ CYN021",
    "Department ‏": "‎ womens",
    "Date First Available ‏": "‎ November 13, 2025",
    "Manufacturer ‏": "‎ Clothfun",
    "ASIN ‏": "‎ B0G2488C58",
    "Product Warranty": "For warranty information about this product, please click here",
    "Best Sellers Rank": "#709,591 in Clothing, Shoes & Jewelry ( See Top 100 in Clothing, Shoes & Jewelry ) #2,341 in Women's Cocktail Dresses #5,213 in Women's Formal Dresses",
    "Customer Reviews": "5.0 5.0 out of 5 stars (7)"
  },
  "category": "Clothing, Shoes & Jewelry > Women > Clothing > Dresses > Cocktail",
  "variations": {
    "sizes": [
      "5",
      "5.5",
      "6",
      "6.5",
      "7",
      "7.5",
      "8",
      "8.5",
      "9",
      "9.5",
      "10",
      "11"
    ],
    "colors": [
      "Dusty Sage",
      "Olive Green",
      "Fuchsia",
      "Dusty Pink",
      "Black",
      "Champagne",
      "Dusty Blue",
      "Orange",
      "Peacock",
      "Plum",
      "Blush Pink",
      "Lavender",
      "Emerald",
      "Royal Blue",
      "Mauve",
      "Light Purple",
      "Teal",
      "Wisteria",
      "Burgundy",
      "Burnt Orange",
      "Hot Pink",
      "Sage",
      "Navy Blue",
      "Light Blue",
      "Mint Green",
      "Red",
      "Lilac",
      "Silver",
      "Pink",
      "Coral",
      "Purple",
      "Yellow",
      "Ocean Blue",
      "Light Burgundy"
    ],
    "size_chart": {
      "label": "Size chart",
      "href": "javascript:void(0)",
      "html": null
    }
  },
  "reviews": {
    "average_rating": 5.0,
    "count": 7,
    "customers_say": null,
    "items": [
      {
        "title": "5.0 out of 5 stars Muy bonito",
        "body": "Muy bonito igual a la foto Read more",
        "author": "Saimara",
        "rating": 5.0,
        "date": "December 10, 2025",
        "verified": false,
        "images": []
      },
      {
        "title": "5.0 out of 5 stars Excelente calidad y acabados",
        "body": "Es muy bonito el vestido, se ve de excelente calidad y el tejido del corset me encantó, llegó antes de lo indicado Read more",
        "author": "ailin",
        "rating": 5.0,
        "date": "November 21, 2025",
        "verified": false,
        "images": []
      },
      {
        "title": "5.0 out of 5 stars Perfect",
        "body": "It was amazing quality with a really good boning. It also wasn’t too short Read more",
        "author": "Havery",
        "rating": 5.0,
        "date": "December 4, 2025",
        "verified": false,
        "images": [
          "https://m.media-amazon.com/images/I/71raOOJaGML._SY88._SL1500_.jpg"
        ]
      },
      {
        "title": "5.0 out of 5 stars Elegant and Stylish",
        "body": "The lace applique adds a delicate touch. I felt so beautiful and elegant wearing it for prom. Read more",
        "author": "mirtin",
        "rating": 5.0,
        "date": "July 24, 2025",
        "verified": false,
        "images": []
      },
      {
        "title": "5.0 out of 5 stars Gorgeous for Homecoming",
        "body": "I wore this dress to my homecoming and felt amazing! The lace details make it so special. Read more",
        "author": "Joe McKinnon",
        "rating": 5.0,
        "date": "July 24, 2025",
        "verified": false,
        "images": []
      }
    ]
  },
  "short_description": "Womens Dress Cocktail is made for a polished look that still feels comfortable to wear. It is designed to sit cleanly on the body with a flattering shape that works for day plans and dressier moments without feeling overdone.\n\nThe fit focuses on balance rather than extremes, so you can move naturally while still getting a defined silhouette. Choose your usual size for a closer look, or size up if you prefer a little more ease through the waist and hips.\n\nStyling is simple: keep accessories minimal for a clean finish, or add a jacket and statement shoes when you want a sharper outfit. This piece photographs well thanks to smooth lines and a structured feel that stays put once you have it adjusted.\n\nWith the right fit and simple styling, this item becomes an easy go-to when you want something that looks intentional without requiring extra effort.\n\nThe design is easy to style with simple accessories and works well in photos thanks to clean lines and a balanced silhouette.\n\nComfort comes from both the cut and the fabric, so selecting your preferred fit makes a noticeable difference over a full day of wear.",
  "about_this_item": "Womens Dress Cocktail is made for a polished look that still feels comfortable to wear. It is designed to sit cleanly on the body with a flattering shape that works for day plans and dressier moments without feeling overdone.\n\nThe fit focuses on balance rather than extremes, so you can move naturally while still getting a defined silhouette. Choose your usual size for a closer look, or size up if you prefer a little more ease through the waist and hips.\n\nStyling is simple: keep accessories minimal for a clean finish, or add a jacket and statement shoes when you want a sharper outfit. This piece photographs well thanks to smooth lines and a structured feel that stays put once you have it adjusted.\n\nWith the right fit and simple styling, this item becomes an easy go-to when you want something that looks intentional without requiring extra effort.\n\nThe design is easy to style with simple accessories and works well in photos thanks to clean lines and a balanced silhouette.\n\nComfort comes from both the cut and the fabric, so selecting your preferred fit makes a noticeable difference over a full day of wear.",
  "long_description": "Womens Dress Cocktail is a versatile piece you can reach for when you want a put-together look that still feels comfortable. The goal is simple: a silhouette that reads polished, photographs well, and stays wearable for a full day or a long night.\n\nFit and sizing Fit is where most outfits win or lose. This design aims for a balanced shape with a defined line through the torso, a clean waist, and a smooth finish through the hips and legs. If you prefer a more relaxed feel, size up; if you like a closer fit, stay true to size. Sizes may include: 5, 5.5, 6, 6.5, 7, 7.5, 8, 8.5, 9, 9.5, 10, 11.\n\nFabric and comfort Comfort is not just about softness. It is also about movement and how the fabric behaves as you walk, sit, and stand. A fabric blend with a bit of give helps it keep its shape while still feeling wearable.\n\nHighlights A clean neckline and a refined silhouette for an elevated look. Designed to layer easily with jackets, wraps, or sweaters. Works well with both minimal accessories and statement pieces.\n\nHow to style Styling ideas: keep it minimal with neutral shoes and one standout accessory. For a relaxed daytime look, add a denim jacket or cardigan. For events, switch to a bolder shoe and a small clutch for a sharper finish.\n\nColor notes Available colors may include: Dusty Sage, Olive Green, Fuchsia, Dusty Pink, Black, Champagne, Dusty Blue, Orange, Peacock, Plum, Blush Pink, Lavender, Emerald, Royal Blue. If a shade is sold out, check back as availability can change.\n\nCare Care guidance matters if you want it to keep its shape and finish. Follow the label first.",
  "long_description_blocks": [
    {
      "type": "p",
      "text": "Womens Dress Cocktail is a versatile piece you can reach for when you want a put-together look that still feels comfortable. The goal is simple: a silhouette that reads polished, photographs well, and stays wearable for a full day or a long night."
    },
    {
      "type": "p",
      "text": "Fit and sizing Fit is where most outfits win or lose. This design aims for a balanced shape with a defined line through the torso, a clean waist, and a smooth finish through the hips and legs. If you prefer a more relaxed feel, size up; if you like a closer fit, stay true to size. Sizes may include: 5, 5.5, 6, 6.5, 7, 7.5, 8, 8.5, 9, 9.5, 10, 11."
    },
    {
      "type": "p",
      "text": "Fabric and comfort Comfort is not just about softness. It is also about movement and how the fabric behaves as you walk, sit, and stand. A fabric blend with a bit of give helps it keep its shape while still feeling wearable."
    },
    {
      "type": "p",
      "text": "Highlights A clean neckline and a refined silhouette for an elevated look. Designed to layer easily with jackets, wraps, or sweaters. Works well with both minimal accessories and statement pieces."
    },
    {
      "type": "p",
      "text": "How to style Styling ideas: keep it minimal with neutral shoes and one standout accessory. For a relaxed daytime look, add a denim jacket or cardigan. For events, switch to a bolder shoe and a small clutch for a sharper finish."
    },
    {
      "type": "p",
      "text": "Color notes Available colors may include: Dusty Sage, Olive Green, Fuchsia, Dusty Pink, Black, Champagne, Dusty Blue, Orange, Peacock, Plum, Blush Pink, Lavender, Emerald, Royal Blue. If a shade is sold out, check back as availability can change."
    },
    {
      "type": "p",
      "text": "Care Care guidance matters if you want it to keep its shape and finish. Follow the label first."
    }
  ],
  "videos": [
    {
      "src": "https://m.media-amazon.com/images/S/al-na-9d5791cf-3faf/a254c10c-a1cd-4cf1-820b-5363f73c72a1.mp4/r/THUMBNAIL_360P_FRAME_3_CAPTURE_2.JPG&quot;,&quot;videoSrc&quot;:&quot;https://m.media-amazon.com/images/S/al-na-9d5791cf-3faf/a254c10c-a1cd-4cf1-820b-5363f73c72a1.mp4/productVideoOptimized.mp4",
      "sources": [
        {
          "type": "video/mp4",
          "src": "https://m.media-amazon.com/images/S/al-na-9d5791cf-3faf/a254c10c-a1cd-4cf1-820b-5363f73c72a1.mp4/r/THUMBNAIL_360P_FRAME_3_CAPTURE_2.JPG&quot;,&quot;videoSrc&quot;:&quot;https://m.media-amazon.com/images/S/al-na-9d5791cf-3faf/a254c10c-a1cd-4cf1-820b-5363f73c72a1.mp4/productVideoOptimized.mp4"
        }
      ]
    },
    {
      "src": "https://m.media-amazon.com/images/S/al-na-9d5791cf-3faf/a254c10c-a1cd-4cf1-820b-5363f73c72a1.mp4/productVideoOptimized.mp4",
      "sources": [
        {
          "type": "video/mp4",
          "src": "https://m.media-amazon.com/images/S/al-na-9d5791cf-3faf/a254c10c-a1cd-4cf1-820b-5363f73c72a1.mp4/productVideoOptimized.mp4"
        }
      ]
    },
    {
      "src": "https://m.media-amazon.com/images/S/al-na-9d5791cf-3faf/a254c10c-a1cd-4cf1-820b-5363f73c72a1.mp4",
      "sources": [
        {
          "type": "video/mp4",
          "src": "https://m.media-amazon.com/images/S/al-na-9d5791cf-3faf/a254c10c-a1cd-4cf1-820b-5363f73c72a1.mp4"
        }
      ]
    },
    {
      "src": "https://m.media-amazon.com/images/S/al-na-9d5791cf-3faf/65aeb37f-0090-43e2-b260-e130aafe066e.mp4/r/THUMBNAIL_360P_FRAME_3_CAPTURE_2.JPG&quot;,&quot;videoSrc&quot;:&quot;https://m.media-amazon.com/images/S/al-na-9d5791cf-3faf/65aeb37f-0090-43e2-b260-e130aafe066e.mp4/productVideoOptimized.mp4",
      "sources": [
        {
          "type": "video/mp4",
          "src": "https://m.media-amazon.com/images/S/al-na-9d5791cf-3faf/65aeb37f-0090-43e2-b260-e130aafe066e.mp4/r/THUMBNAIL_360P_FRAME_3_CAPTURE_2.JPG&quot;,&quot;videoSrc&quot;:&quot;https://m.media-amazon.com/images/S/al-na-9d5791cf-3faf/65aeb37f-0090-43e2-b260-e130aafe066e.mp4/productVideoOptimized.mp4"
        }
      ]
    },
    {
      "src": "https://m.media-amazon.com/images/S/al-na-9d5791cf-3faf/65aeb37f-0090-43e2-b260-e130aafe066e.mp4/productVideoOptimized.mp4",
      "sources": [
        {
          "type": "video/mp4",
          "src": "https://m.media-amazon.com/images/S/al-na-9d5791cf-3faf/65aeb37f-0090-43e2-b260-e130aafe066e.mp4/productVideoOptimized.mp4"
        }
      ]
    },
    {
      "src": "https://m.media-amazon.com/images/S/al-na-9d5791cf-3faf/65aeb37f-0090-43e2-b260-e130aafe066e.mp4",
      "sources": [
        {
          "type": "video/mp4",
          "src": "https://m.media-amazon.com/images/S/al-na-9d5791cf-3faf/65aeb37f-0090-43e2-b260-e130aafe066e.mp4"
        }
      ]
    },
    {
      "src": "https://m.media-amazon.com/images/S/al-na-9d5791cf-3faf/ad949e3c-9e3e-4834-a04e-7c6b4443e87c.mp4/r/THUMBNAIL_360P_FRAME_3_CAPTURE_2.JPG&quot;,&quot;videoSrc&quot;:&quot;https://m.media-amazon.com/images/S/al-na-9d5791cf-3faf/ad949e3c-9e3e-4834-a04e-7c6b4443e87c.mp4/productVideoOptimized.mp4",
      "sources": [
        {
          "type": "video/mp4",
          "src": "https://m.media-amazon.com/images/S/al-na-9d5791cf-3faf/ad949e3c-9e3e-4834-a04e-7c6b4443e87c.mp4/r/THUMBNAIL_360P_FRAME_3_CAPTURE_2.JPG&quot;,&quot;videoSrc&quot;:&quot;https://m.media-amazon.com/images/S/al-na-9d5791cf-3faf/ad949e3c-9e3e-4834-a04e-7c6b4443e87c.mp4/productVideoOptimized.mp4"
        }
      ]
    },
    {
      "src": "https://m.media-amazon.com/images/S/al-na-9d5791cf-3faf/ad949e3c-9e3e-4834-a04e-7c6b4443e87c.mp4/productVideoOptimized.mp4",
      "sources": [
        {
          "type": "video/mp4",
          "src": "https://m.media-amazon.com/images/S/al-na-9d5791cf-3faf/ad949e3c-9e3e-4834-a04e-7c6b4443e87c.mp4/productVideoOptimized.mp4"
        }
      ]
    },
    {
      "src": "https://m.media-amazon.com/images/S/al-na-9d5791cf-3faf/ad949e3c-9e3e-4834-a04e-7c6b4443e87c.mp4",
      "sources": [
        {
          "type": "video/mp4",
          "src": "https://m.media-amazon.com/images/S/al-na-9d5791cf-3faf/ad949e3c-9e3e-4834-a04e-7c6b4443e87c.mp4"
        }
      ]
    },
    {
      "src": "https://m.media-amazon.com/images/S/al-na-9d5791cf-3faf/e762c1da-3a2c-45c0-9472-90b6907ed2c2.mp4/r/THUMBNAIL_360P_FRAME_3_CAPTURE_2.JPG&quot;,&quot;videoSrc&quot;:&quot;https://m.media-amazon.com/images/S/al-na-9d5791cf-3faf/e762c1da-3a2c-45c0-9472-90b6907ed2c2.mp4/productVideoOptimized.mp4",
      "sources": [
        {
          "type": "video/mp4",
          "src": "https://m.media-amazon.com/images/S/al-na-9d5791cf-3faf/e762c1da-3a2c-45c0-9472-90b6907ed2c2.mp4/r/THUMBNAIL_360P_FRAME_3_CAPTURE_2.JPG&quot;,&quot;videoSrc&quot;:&quot;https://m.media-amazon.com/images/S/al-na-9d5791cf-3faf/e762c1da-3a2c-45c0-9472-90b6907ed2c2.mp4/productVideoOptimized.mp4"
        }
      ]
    },
    {
      "src": "https://m.media-amazon.com/images/S/al-na-9d5791cf-3faf/e762c1da-3a2c-45c0-9472-90b6907ed2c2.mp4/productVideoOptimized.mp4",
      "sources": [
        {
          "type": "video/mp4",
          "src": "https://m.media-amazon.com/images/S/al-na-9d5791cf-3faf/e762c1da-3a2c-45c0-9472-90b6907ed2c2.mp4/productVideoOptimized.mp4"
        }
      ]
    },
    {
      "src": "https://m.media-amazon.com/images/S/al-na-9d5791cf-3faf/e762c1da-3a2c-45c0-9472-90b6907ed2c2.mp4",
      "sources": [
        {
          "type": "video/mp4",
          "src": "https://m.media-amazon.com/images/S/al-na-9d5791cf-3faf/e762c1da-3a2c-45c0-9472-90b6907ed2c2.mp4"
        }
      ]
    }
  ],
  "color_swatches": {
    "Dusty Sage": "https://m.media-amazon.com/images/I/31bf4FNhY+L._AC_SR38,50_.jpg",
    "Olive Green": "https://m.media-amazon.com/images/I/415oJCj4V4L._AC_SR38,50_.jpg",
    "Fuchsia": "https://m.media-amazon.com/images/I/31CV+a8xBTL._AC_SR38,50_.jpg",
    "Dusty Pink": "https://m.media-amazon.com/images/I/31M-agIe9yL._AC_SR38,50_.jpg",
    "Black": "https://m.media-amazon.com/images/I/31Bb1JmO+gL._AC_SR38,50_.jpg",
    "Champagne": "https://m.media-amazon.com/images/I/310zVWxe+qL._AC_SR38,50_.jpg",
    "Dusty Blue": "https://m.media-amazon.com/images/I/31Wp2ZdwYxL._AC_SR38,50_.jpg",
    "Orange": "https://m.media-amazon.com/images/I/31QfQ9dVs9L._AC_SR38,50_.jpg",
    "Peacock": "https://m.media-amazon.com/images/I/312HHPHZPKL._AC_SR38,50_.jpg",
    "Plum": "https://m.media-amazon.com/images/I/31DGbA2QgHL._AC_SR38,50_.jpg",
    "Blush Pink": "https://m.media-amazon.com/images/I/31II4BetxyL._AC_SR38,50_.jpg",
    "Lavender": "https://m.media-amazon.com/images/I/31iE6rVOp9L._AC_SR38,50_.jpg",
    "Emerald": "https://m.media-amazon.com/images/I/31zLoxytAtL._AC_SR38,50_.jpg",
    "Royal Blue": "https://m.media-amazon.com/images/I/41Zlmcbzj6L._AC_SR38,50_.jpg",
    "Mauve": "https://m.media-amazon.com/images/I/31IEK1xEC7L._AC_SR38,50_.jpg",
    "Light Purple": "https://m.media-amazon.com/images/I/31UP++ZMHTL._AC_SR38,50_.jpg",
    "Teal": "https://m.media-amazon.com/images/I/4198JkftzxL._AC_SR38,50_.jpg",
    "Wisteria": "https://m.media-amazon.com/images/I/31dMJyQCL0L._AC_SR38,50_.jpg",
    "Burgundy": "https://m.media-amazon.com/images/I/31U56ONQp-L._AC_SR38,50_.jpg",
    "Burnt Orange": "https://m.media-amazon.com/images/I/41EBeOW5ohL._AC_SR38,50_.jpg",
    "Hot Pink": "https://m.media-amazon.com/images/I/31VP2Zx6TJL._AC_SR38,50_.jpg",
    "Sage": "https://m.media-amazon.com/images/I/310ybct6AlL._AC_SR38,50_.jpg",
    "Navy Blue": "https://m.media-amazon.com/images/I/31PRwGsKW1L._AC_SR38,50_.jpg",
    "Light Blue": "https://m.media-amazon.com/images/I/316rTeShZxL._AC_SR38,50_.jpg",
    "Mint Green": "https://m.media-amazon.com/images/I/31KygqGft3L._AC_SR38,50_.jpg",
    "Red": "https://m.media-amazon.com/images/I/41fn1tEGzPL._AC_SR38,50_.jpg",
    "Lilac": "https://m.media-amazon.com/images/I/31MIRhTBVKL._AC_SR38,50_.jpg",
    "Silver": "https://m.media-amazon.com/images/I/31Gzlf+Er3L._AC_SR38,50_.jpg",
    "Pink": "https://m.media-amazon.com/images/I/31l0Ulu5ReL._AC_SR38,50_.jpg",
    "Coral": "https://m.media-amazon.com/images/I/31l7V4Q3+BL._AC_SR38,50_.jpg",
    "Purple": "https://m.media-amazon.com/images/I/41w0LXt7GvL._AC_SR38,50_.jpg",
    "Yellow": "https://m.media-amazon.com/images/I/214naBLZVrL._AC_SR38,50_.jpg",
    "Ocean Blue": "https://m.media-amazon.com/images/I/31mEyFnL42L._AC_SR38,50_.jpg",
    "Light Burgundy": "https://m.media-amazon.com/images/I/31LgpNg5-RL._AC_SR38,50_.jpg"
  },
  "color_image_key": {
    "Dusty Sage": "61c3n934J2L",
    "Olive Green": "71tKdkC6qaL",
    "Fuchsia": "61Uwx1afQiL",
    "Dusty Pink": "61rL6vrGQXL",
    "Black": "71cMdetxX5L",
    "Champagne": "617iRRTTNOL",
    "Dusty Blue": "61DWMEm-oaL",
    "Orange": "71CDhJlZRvL",
    "Peacock": "71IBCMdSXaL",
    "Plum": "61XDZMwfPLL",
    "Blush Pink": "61XMVIYiEVL",
    "Lavender": "617tvwtwMnL",
    "Emerald": "71I5l0BNRBL",
    "Royal Blue": "71P4KtckE4L",
    "Mauve": "61IoX2nZexL",
    "Light Purple": "61birFuLt0L",
    "Teal": "71QmlLOhf3L",
    "Wisteria": "61wUqxxA+eL",
    "Burgundy": "61SKYwzsSpL",
    "Burnt Orange": "71CvGS0UPBL",
    "Hot Pink": "61aiWUAi7kL",
    "Sage": "61HGSyfIoTL",
    "Navy Blue": "61bZ5vGe8TL",
    "Light Blue": "61peYm1Q-RL",
    "Mint Green": "615H9MtRSCL",
    "Red": "718nP2GsRoL",
    "Lilac": "61yJWgQSq0L",
    "Silver": "61QkDNsdF2L",
    "Pink": "616R42slmRL",
    "Coral": "71LYIqO5n2L",
    "Purple": "71nIrNzRpsL",
    "Yellow": "612OYlbShuL",
    "Ocean Blue": "71Dcjg1D3OL",
    "Light Burgundy": "61s1Y0PNlXL"
  },
  "color_images": {
    "Dusty Sage": [
      "https://m.media-amazon.com/images/I/61c3n934J2L._SL1500_.jpg",
      "https://m.media-amazon.com/images/I/617tvwtwMnL._SL1500_.jpg",
      "https://m.media-amazon.com/images/I/61peYm1Q-RL._SL1500_.jpg",
      "https://m.media-amazon.com/images/I/617iRRTTNOL._SL1500_.jpg",
      "https://m.media-amazon.com/images/I/612OYlbShuL._SL1500_.jpg",
      "https://m.media-amazon.com/images/I/61HGSyfIoTL._SL1500_.jpg"
    ],
    "Olive Green": [
      "https://m.media-amazon.com/images/I/71tKdkC6qaL._SL1500_.jpg",
      "https://m.media-amazon.com/images/I/617tvwtwMnL._SL1500_.jpg",
      "https://m.media-amazon.com/images/I/61peYm1Q-RL._SL1500_.jpg",
      "https://m.media-amazon.com/images/I/617iRRTTNOL._SL1500_.jpg",
      "https://m.media-amazon.com/images/I/612OYlbShuL._SL1500_.jpg",
      "https://m.media-amazon.com/images/I/61HGSyfIoTL._SL1500_.jpg"
    ],
    "Fuchsia": [
      "https://m.media-amazon.com/images/I/61Uwx1afQiL._SL1500_.jpg",
      "https://m.media-amazon.com/images/I/617tvwtwMnL._SL1500_.jpg",
      "https://m.media-amazon.com/images/I/61peYm1Q-RL._SL1500_.jpg",
      "https://m.media-amazon.com/images/I/617iRRTTNOL._SL1500_.jpg",
      "https://m.media-amazon.com/images/I/612OYlbShuL._SL1500_.jpg",
      "https://m.media-amazon.com/images/I/61HGSyfIoTL._SL1500_.jpg"
    ],
    "Dusty Pink": [
      "https://m.media-amazon.com/images/I/61rL6vrGQXL._SL1500_.jpg",
      "https://m.media-amazon.com/images/I/617tvwtwMnL._SL1500_.jpg",
      "https://m.media-amazon.com/images/I/61peYm1Q-RL._SL1500_.jpg",
      "https://m.media-amazon.com/images/I/617iRRTTNOL._SL1500_.jpg",
      "https://m.media-amazon.com/images/I/612OYlbShuL._SL1500_.jpg",
      "https://m.media-amazon.com/images/I/61HGSyfIoTL._SL1500_.jpg"
    ],
    "Black": [
      "https://m.media-amazon.com/images/I/71cMdetxX5L._SL1500_.jpg",
      "https://m.media-amazon.com/images/I/617tvwtwMnL._SL1500_.jpg",
      "https://m.media-amazon.com/images/I/61peYm1Q-RL._SL1500_.jpg",
      "https://m.media-amazon.com/images/I/617iRRTTNOL._SL1500_.jpg",
      "https://m.media-amazon.com/images/I/612OYlbShuL._SL1500_.jpg",
      "https://m.media-amazon.com/images/I/61HGSyfIoTL._SL1500_.jpg"
    ],
    "Champagne": [
      "https://m.media-amazon.com/images/I/617iRRTTNOL._SL1500_.jpg",
      "https://m.media-amazon.com/images/I/617tvwtwMnL._SL1500_.jpg",
      "https://m.media-amazon.com/images/I/61peYm1Q-RL._SL1500_.jpg",
      "https://m.media-amazon.com/images/I/612OYlbShuL._SL1500_.jpg",
      "https://m.media-amazon.com/images/I/61HGSyfIoTL._SL1500_.jpg"
    ],
    "Dusty Blue": [
      "https://m.media-amazon.com/images/I/61DWMEm-oaL._SL1500_.jpg",
      "https://m.media-amazon.com/images/I/617tvwtwMnL._SL1500_.jpg",
      "https://m.media-amazon.com/images/I/61peYm1Q-RL._SL1500_.jpg",
      "https://m.media-amazon.com/images/I/617iRRTTNOL._SL1500_.jpg",
      "https://m.media-amazon.com/images/I/612OYlbShuL._SL1500_.jpg",
      "https://m.media-amazon.com/images/I/61HGSyfIoTL._SL1500_.jpg"
    ],
    "Orange": [
      "https://m.media-amazon.com/images/I/71CDhJlZRvL._SL1500_.jpg",
      "https://m.media-amazon.com/images/I/617tvwtwMnL._SL1500_.jpg",
      "https://m.media-amazon.com/images/I/61peYm1Q-RL._SL1500_.jpg",
      "https://m.media-amazon.com/images/I/617iRRTTNOL._SL1500_.jpg",
      "https://m.media-amazon.com/images/I/612OYlbShuL._SL1500_.jpg",
      "https://m.media-amazon.com/images/I/61HGSyfIoTL._SL1500_.jpg"
    ],
    "Peacock": [
      "https://m.media-amazon.com/images/I/71IBCMdSXaL._SL1500_.jpg",
      "https://m.media-amazon.com/images/I/617tvwtwMnL._SL1500_.jpg",
      "https://m.media-amazon.com/images/I/61peYm1Q-RL._SL1500_.jpg",
      "https://m.media-amazon.com/images/I/617iRRTTNOL._SL1500_.jpg",
      "https://m.media-amazon.com/images/I/612OYlbShuL._SL1500_.jpg",
      "https://m.media-amazon.com/images/I/61HGSyfIoTL._SL1500_.jpg"
    ],
    "Plum": [
      "https://m.media-amazon.com/images/I/61XDZMwfPLL._SL1500_.jpg",
      "https://m.media-amazon.com/images/I/617tvwtwMnL._SL1500_.jpg",
      "https://m.media-amazon.com/images/I/61peYm1Q-RL._SL1500_.jpg",
      "https://m.media-amazon.com/images/I/617iRRTTNOL._SL1500_.jpg",
      "https://m.media-amazon.com/images/I/612OYlbShuL._SL1500_.jpg",
      "https://m.media-amazon.com/images/I/61HGSyfIoTL._SL1500_.jpg"
    ],
    "Blush Pink": [
      "https://m.media-amazon.com/images/I/61XMVIYiEVL._SL1500_.jpg",
      "https://m.media-amazon.com/images/I/617tvwtwMnL._SL1500_.jpg",
      "https://m.media-amazon.com/images/I/61peYm1Q-RL._SL1500_.jpg",
      "https://m.media-amazon.com/images/I/617iRRTTNOL._SL1500_.jpg",
      "https://m.media-amazon.com/images/I/612OYlbShuL._SL1500_.jpg",
      "https://m.media-amazon.com/images/I/61HGSyfIoTL._SL1500_.jpg"
    ],
    "Lavender": [
      "https://m.media-amazon.com/images/I/617tvwtwMnL._SL1500_.jpg",
      "https://m.media-amazon.com/images/I/61peYm1Q-RL._SL1500_.jpg",
      "https://m.media-amazon.com/images/I/617iRRTTNOL._SL1500_.jpg",
      "https://m.media-amazon.com/images/I/612OYlbShuL._SL1500_.jpg",
      "https://m.media-amazon.com/images/I/61HGSyfIoTL._SL1500_.jpg"
    ],
    "Emerald": [
      "https://m.media-amazon.com/images/I/71I5l0BNRBL._SL1500_.jpg",
      "https://m.media-amazon.com/images/I/617tvwtwMnL._SL1500_.jpg",
      "https://m.media-amazon.com/images/I/61peYm1Q-RL._SL1500_.jpg",
      "https://m.media-amazon.com/images/I/617iRRTTNOL._SL1500_.jpg",
      "https://m.media-amazon.com/images/I/612OYlbShuL._SL1500_.jpg",
      "https://m.media-amazon.com/images/I/61HGSyfIoTL._SL1500_.jpg"
    ],
    "Royal Blue": [
      "https://m.media-amazon.com/images/I/71P4KtckE4L._SL1500_.jpg",
      "https://m.media-amazon.com/images/I/617tvwtwMnL._SL1500_.jpg",
      "https://m.media-amazon.com/images/I/61peYm1Q-RL._SL1500_.jpg",
      "https://m.media-amazon.com/images/I/617iRRTTNOL._SL1500_.jpg",
      "https://m.media-amazon.com/images/I/612OYlbShuL._SL1500_.jpg",
      "https://m.media-amazon.com/images/I/61HGSyfIoTL._SL1500_.jpg"
    ],
    "Mauve": [
      "https://m.media-amazon.com/images/I/61IoX2nZexL._SL1500_.jpg",
      "https://m.media-amazon.com/images/I/617tvwtwMnL._SL1500_.jpg",
      "https://m.media-amazon.com/images/I/61peYm1Q-RL._SL1500_.jpg",
      "https://m.media-amazon.com/images/I/617iRRTTNOL._SL1500_.jpg",
      "https://m.media-amazon.com/images/I/612OYlbShuL._SL1500_.jpg",
      "https://m.media-amazon.com/images/I/61HGSyfIoTL._SL1500_.jpg"
    ],
    "Light Purple": [
      "https://m.media-amazon.com/images/I/61birFuLt0L._SL1500_.jpg",
      "https://m.media-amazon.com/images/I/617tvwtwMnL._SL1500_.jpg",
      "https://m.media-amazon.com/images/I/61peYm1Q-RL._SL1500_.jpg",
      "https://m.media-amazon.com/images/I/617iRRTTNOL._SL1500_.jpg",
      "https://m.media-amazon.com/images/I/612OYlbShuL._SL1500_.jpg",
      "https://m.media-amazon.com/images/I/61HGSyfIoTL._SL1500_.jpg"
    ],
    "Teal": [
      "https://m.media-amazon.com/images/I/71QmlLOhf3L._SL1500_.jpg",
      "https://m.media-amazon.com/images/I/617tvwtwMnL._SL1500_.jpg",
      "https://m.media-amazon.com/images/I/61peYm1Q-RL._SL1500_.jpg",
      "https://m.media-amazon.com/images/I/617iRRTTNOL._SL1500_.jpg",
      "https://m.media-amazon.com/images/I/612OYlbShuL._SL1500_.jpg",
      "https://m.media-amazon.com/images/I/61HGSyfIoTL._SL1500_.jpg"
    ],
    "Wisteria": [
      "https://m.media-amazon.com/images/I/61wUqxxA+eL._SL1500_.jpg",
      "https://m.media-amazon.com/images/I/617tvwtwMnL._SL1500_.jpg",
      "https://m.media-amazon.com/images/I/61peYm1Q-RL._SL1500_.jpg",
      "https://m.media-amazon.com/images/I/617iRRTTNOL._SL1500_.jpg",
      "https://m.media-amazon.com/images/I/612OYlbShuL._SL1500_.jpg",
      "https://m.media-amazon.com/images/I/61HGSyfIoTL._SL1500_.jpg"
    ],
    "Burgundy": [
      "https://m.media-amazon.com/images/I/61SKYwzsSpL._SL1500_.jpg",
      "https://m.media-amazon.com/images/I/617tvwtwMnL._SL1500_.jpg",
      "https://m.media-amazon.com/images/I/61peYm1Q-RL._SL1500_.jpg",
      "https://m.media-amazon.com/images/I/617iRRTTNOL._SL1500_.jpg",
      "https://m.media-amazon.com/images/I/612OYlbShuL._SL1500_.jpg",
      "https://m.media-amazon.com/images/I/61HGSyfIoTL._SL1500_.jpg"
    ],
    "Burnt Orange": [
      "https://m.media-amazon.com/images/I/71CvGS0UPBL._SL1500_.jpg",
      "https://m.media-amazon.com/images/I/617tvwtwMnL._SL1500_.jpg",
      "https://m.media-amazon.com/images/I/61peYm1Q-RL._SL1500_.jpg",
      "https://m.media-amazon.com/images/I/617iRRTTNOL._SL1500_.jpg",
      "https://m.media-amazon.com/images/I/612OYlbShuL._SL1500_.jpg",
      "https://m.media-amazon.com/images/I/61HGSyfIoTL._SL1500_.jpg"
    ],
    "Hot Pink": [
      "https://m.media-amazon.com/images/I/61aiWUAi7kL._SL1500_.jpg",
      "https://m.media-amazon.com/images/I/617tvwtwMnL._SL1500_.jpg",
      "https://m.media-amazon.com/images/I/61peYm1Q-RL._SL1500_.jpg",
      "https://m.media-amazon.com/images/I/617iRRTTNOL._SL1500_.jpg",
      "https://m.media-amazon.com/images/I/612OYlbShuL._SL1500_.jpg",
      "https://m.media-amazon.com/images/I/61HGSyfIoTL._SL1500_.jpg"
    ],
    "Sage": [
      "https://m.media-amazon.com/images/I/61HGSyfIoTL._SL1500_.jpg",
      "https://m.media-amazon.com/images/I/617tvwtwMnL._SL1500_.jpg",
      "https://m.media-amazon.com/images/I/61peYm1Q-RL._SL1500_.jpg",
      "https://m.media-amazon.com/images/I/617iRRTTNOL._SL1500_.jpg",
      "https://m.media-amazon.com/images/I/612OYlbShuL._SL1500_.jpg"
    ],
    "Navy Blue": [
      "https://m.media-amazon.com/images/I/61bZ5vGe8TL._SL1500_.jpg",
      "https://m.media-amazon.com/images/I/617tvwtwMnL._SL1500_.jpg",
      "https://m.media-amazon.com/images/I/61peYm1Q-RL._SL1500_.jpg",
      "https://m.media-amazon.com/images/I/617iRRTTNOL._SL1500_.jpg",
      "https://m.media-amazon.com/images/I/612OYlbShuL._SL1500_.jpg",
      "https://m.media-amazon.com/images/I/61HGSyfIoTL._SL1500_.jpg"
    ],
    "Light Blue": [
      "https://m.media-amazon.com/images/I/61peYm1Q-RL._SL1500_.jpg",
      "https://m.media-amazon.com/images/I/617tvwtwMnL._SL1500_.jpg",
      "https://m.media-amazon.com/images/I/617iRRTTNOL._SL1500_.jpg",
      "https://m.media-amazon.com/images/I/612OYlbShuL._SL1500_.jpg",
      "https://m.media-amazon.com/images/I/61HGSyfIoTL._SL1500_.jpg"
    ],
    "Mint Green": [
      "https://m.media-amazon.com/images/I/615H9MtRSCL._SL1500_.jpg",
      "https://m.media-amazon.com/images/I/617tvwtwMnL._SL1500_.jpg",
      "https://m.media-amazon.com/images/I/61peYm1Q-RL._SL1500_.jpg",
      "https://m.media-amazon.com/images/I/617iRRTTNOL._SL1500_.jpg",
      "https://m.media-amazon.com/images/I/612OYlbShuL._SL1500_.jpg",
      "https://m.media-amazon.com/images/I/61HGSyfIoTL._SL1500_.jpg"
    ],
    "Red": [
      "https://m.media-amazon.com/images/I/718nP2GsRoL._SL1500_.jpg",
      "https://m.media-amazon.com/images/I/617tvwtwMnL._SL1500_.jpg",
      "https://m.media-amazon.com/images/I/61peYm1Q-RL._SL1500_.jpg",
      "https://m.media-amazon.com/images/I/617iRRTTNOL._SL1500_.jpg",
      "https://m.media-amazon.com/images/I/612OYlbShuL._SL1500_.jpg",
      "https://m.media-amazon.com/images/I/61HGSyfIoTL._SL1500_.jpg"
    ],
    "Lilac": [
      "https://m.media-amazon.com/images/I/61yJWgQSq0L._SL1500_.jpg",
      "https://m.media-amazon.com/images/I/617tvwtwMnL._SL1500_.jpg",
      "https://m.media-amazon.com/images/I/61peYm1Q-RL._SL1500_.jpg",
      "https://m.media-amazon.com/images/I/617iRRTTNOL._SL1500_.jpg",
      "https://m.media-amazon.com/images/I/612OYlbShuL._SL1500_.jpg",
      "https://m.media-amazon.com/images/I/61HGSyfIoTL._SL1500_.jpg"
    ],
    "Silver": [
      "https://m.media-amazon.com/images/I/61QkDNsdF2L._SL1500_.jpg",
      "https://m.media-amazon.com/images/I/617tvwtwMnL._SL1500_.jpg",
      "https://m.media-amazon.com/images/I/61peYm1Q-RL._SL1500_.jpg",
      "https://m.media-amazon.com/images/I/617iRRTTNOL._SL1500_.jpg",
      "https://m.media-amazon.com/images/I/612OYlbShuL._SL1500_.jpg",
      "https://m.media-amazon.com/images/I/61HGSyfIoTL._SL1500_.jpg"
    ],
    "Pink": [
      "https://m.media-amazon.com/images/I/616R42slmRL._SL1500_.jpg",
      "https://m.media-amazon.com/images/I/617tvwtwMnL._SL1500_.jpg",
      "https://m.media-amazon.com/images/I/61peYm1Q-RL._SL1500_.jpg",
      "https://m.media-amazon.com/images/I/617iRRTTNOL._SL1500_.jpg",
      "https://m.media-amazon.com/images/I/612OYlbShuL._SL1500_.jpg",
      "https://m.media-amazon.com/images/I/61HGSyfIoTL._SL1500_.jpg"
    ],
    "Coral": [
      "https://m.media-amazon.com/images/I/71LYIqO5n2L._SL1500_.jpg",
      "https://m.media-amazon.com/images/I/617tvwtwMnL._SL1500_.jpg",
      "https://m.media-amazon.com/images/I/61peYm1Q-RL._SL1500_.jpg",
      "https://m.media-amazon.com/images/I/617iRRTTNOL._SL1500_.jpg",
      "https://m.media-amazon.com/images/I/612OYlbShuL._SL1500_.jpg",
      "https://m.media-amazon.com/images/I/61HGSyfIoTL._SL1500_.jpg"
    ],
    "Purple": [
      "https://m.media-amazon.com/images/I/71nIrNzRpsL._SL1500_.jpg",
      "https://m.media-amazon.com/images/I/617tvwtwMnL._SL1500_.jpg",
      "https://m.media-amazon.com/images/I/61peYm1Q-RL._SL1500_.jpg",
      "https://m.media-amazon.com/images/I/617iRRTTNOL._SL1500_.jpg",
      "https://m.media-amazon.com/images/I/612OYlbShuL._SL1500_.jpg",
      "https://m.media-amazon.com/images/I/61HGSyfIoTL._SL1500_.jpg"
    ],
    "Yellow": [
      "https://m.media-amazon.com/images/I/612OYlbShuL._SL1500_.jpg",
      "https://m.media-amazon.com/images/I/617tvwtwMnL._SL1500_.jpg",
      "https://m.media-amazon.com/images/I/61peYm1Q-RL._SL1500_.jpg",
      "https://m.media-amazon.com/images/I/617iRRTTNOL._SL1500_.jpg",
      "https://m.media-amazon.com/images/I/61HGSyfIoTL._SL1500_.jpg"
    ],
    "Ocean Blue": [
      "https://m.media-amazon.com/images/I/71Dcjg1D3OL._SL1500_.jpg",
      "https://m.media-amazon.com/images/I/617tvwtwMnL._SL1500_.jpg",
      "https://m.media-amazon.com/images/I/61peYm1Q-RL._SL1500_.jpg",
      "https://m.media-amazon.com/images/I/617iRRTTNOL._SL1500_.jpg",
      "https://m.media-amazon.com/images/I/612OYlbShuL._SL1500_.jpg",
      "https://m.media-amazon.com/images/I/61HGSyfIoTL._SL1500_.jpg"
    ],
    "Light Burgundy": [
      "https://m.media-amazon.com/images/I/61s1Y0PNlXL._SL1500_.jpg",
      "https://m.media-amazon.com/images/I/617tvwtwMnL._SL1500_.jpg",
      "https://m.media-amazon.com/images/I/61peYm1Q-RL._SL1500_.jpg",
      "https://m.media-amazon.com/images/I/617iRRTTNOL._SL1500_.jpg",
      "https://m.media-amazon.com/images/I/612OYlbShuL._SL1500_.jpg",
      "https://m.media-amazon.com/images/I/61HGSyfIoTL._SL1500_.jpg"
    ]
  },
  "related": [
    {
      "id": "womens-maxi-dress-ruched-long-sleeve-off-shoulder",
      "title": "Womens Maxi Dress Ruched Long Sleeve Off Shoulder",
      "price": 65.99,
      "category": "Clothing, Shoes & Jewelry > Women > Clothing > Dresses > Formal",
      "images": [
        "https://m.media-amazon.com/images/I/610S-XUGzwL._SL1500_.jpg"
      ]
    },
    {
      "id": "womens-maxi-dress-sleeveless-v-neck-cocktail-maxi-bodycon",
      "title": "Womens Maxi Dress Sleeveless V Neck Cocktail Maxi Bodycon",
      "price": 44.99,
      "category": "Clothing, Shoes & Jewelry > Women > Clothing > Dresses > Club & Night Out",
      "images": [
        "https://m.media-amazon.com/images/I/51eoMzKwaqL._SL1500_.jpg"
      ]
    },
    {
      "id": "womens-maxi-dress-long-sleeve-formal-cocktail",
      "title": "Womens Maxi Dress Long Sleeve Formal Cocktail",
      "price": 45.99,
      "category": "Clothing, Shoes & Jewelry > Women > Clothing > Dresses",
      "images": [
        "https://m.media-amazon.com/images/I/610egGe2LwL._SL1500_.jpg"
      ]
    },
    {
      "id": "womens-maxi-dress-long-sleeve-v-neck-ruched",
      "title": "Womens Maxi Dress Long Sleeve V Neck Ruched",
      "price": 41.99,
      "category": "Clothing, Shoes & Jewelry > Women > Clothing > Dresses > Club & Night Out",
      "images": [
        "https://m.media-amazon.com/images/I/41nKZb3yrHL._SL1500_.jpg"
      ]
    },
    {
      "id": "womens-maxi-dress-long-sleeve",
      "title": "Womens Maxi Dress Long Sleeve",
      "price": 33.99,
      "category": "Clothing, Shoes & Jewelry > Women > Clothing > Dresses > Club & Night Out",
      "images": [
        "https://m.media-amazon.com/images/I/61W5l+uioHL._SL1500_.jpg"
      ]
    }
  ],
  "customer_also_viewed": [
    {
      "id": "womens-maxi-dress-evening",
      "title": "Womens Maxi Dress Evening",
      "price": 72.99,
      "category": "Clothing, Shoes & Jewelry > Women > Clothing > Dresses > Formal",
      "images": [
        "https://m.media-amazon.com/images/I/61ifQNM1WAL._SL1500_.jpg"
      ]
    },
    {
      "id": "womens-maxi-dress-evening",
      "title": "Womens Maxi Dress Evening",
      "price": 66.99,
      "category": "Clothing, Shoes & Jewelry > Women > Clothing > Dresses > Formal",
      "images": [
        "https://m.media-amazon.com/images/I/61jhboT-KdL._SL1500_.jpg"
      ]
    },
    {
      "id": "womens-maxi-dress-cocktail-bodycon-ruched-off-shoulder",
      "title": "Womens Maxi Dress Cocktail Bodycon Ruched Off Shoulder",
      "price": 39.99,
      "category": "Clothing, Shoes & Jewelry > Women > Clothing > Dresses > Cocktail",
      "images": [
        "https://m.media-amazon.com/images/I/51pNtXYlEDL._SL1500_.jpg"
      ]
    },
    {
      "id": "womens-dress",
      "title": "Womens Dress",
      "price": 70.57,
      "category": "Clothing, Shoes & Jewelry > Women > Clothing > Dresses > Casual",
      "images": [
        "https://m.media-amazon.com/images/I/512WgWMyYLL._SL1500_.jpg"
      ]
    },
    {
      "id": "womens-maxi-dress-evening-one-shoulder-formal-mermaid",
      "title": "Womens Maxi Dress Evening One Shoulder Formal Mermaid",
      "price": 69.99,
      "category": "Clothing, Shoes & Jewelry > Women > Clothing > Dresses > Formal",
      "images": [
        "https://m.media-amazon.com/images/I/613xHpbpN5L._SL1500_.jpg"
      ]
    },
    {
      "id": "womens-dress-off-shoulder",
      "title": "Womens Dress Off Shoulder",
      "price": 93.99,
      "category": "Clothing, Shoes & Jewelry > Women > Clothing > Dresses > Formal",
      "images": [
        "https://m.media-amazon.com/images/I/71+G9PIEq1L._SL1500_.jpg"
      ]
    },
    {
      "id": "womens-dress-short-sleeve",
      "title": "Womens Dress Short Sleeve",
      "price": 59.99,
      "category": "Clothing, Shoes & Jewelry > Women > Clothing > Dresses > Casual",
      "images": [
        "https://m.media-amazon.com/images/I/61Gm5oBtjDL._SL1500_.jpg"
      ]
    },
    {
      "id": "womens-dress-bodycon-cocktail",
      "title": "Womens Dress Bodycon Cocktail",
      "price": 55.99,
      "category": "Clothing, Shoes & Jewelry > Women > Clothing > Dresses > Club & Night Out",
      "images": [
        "https://m.media-amazon.com/images/I/61k-qoz2M6L._SL1500_.jpg"
      ]
    }
  ]
}