{
  "id": "womens-maxi-dress-mermaid-short-sleeve-formal",
  "handle": "womens-maxi-dress-mermaid-short-sleeve-formal",
  "sku": "JC2539",
  "asin": "B0G6DQKYKR",
  "title": "Womens Maxi Dress Mermaid Short Sleeve Formal",
  "title_original": "Short Sleeves Mother of The Bride Dresses for Women Mermaid Sequin Chiffon Long Formal Wedding Guest Dress with Train",
  "brand": "Visit the Skbue Store",
  "price": 79.99,
  "social_proof": {
    "bought_past_month": 545,
    "text": "545+ bought in the past month"
  },
  "images": [
    "https://m.media-amazon.com/images/I/61ODaWZ8uJL._SL1500_.jpg",
    "https://m.media-amazon.com/images/I/71HTV7xAsqL._SL1500_.jpg",
    "https://m.media-amazon.com/images/I/714AFJ345mL._SL1500_.jpg",
    "https://m.media-amazon.com/images/I/71slq7f5seL._SL1500_.jpg",
    "https://m.media-amazon.com/images/I/71SkpMs8AjL._SL1500_.jpg",
    "https://m.media-amazon.com/images/I/71M9cVP3BDL._SL1500_.jpg",
    "https://m.media-amazon.com/images/I/7111QzGravL._SL1500_.jpg",
    "https://m.media-amazon.com/images/I/61h1AhS4CNL._SL1500_.jpg",
    "https://m.media-amazon.com/images/I/61LXS2IeA0L._SL1500_.jpg",
    "https://m.media-amazon.com/images/I/615X6SlFD-L._SL1500_.jpg",
    "https://m.media-amazon.com/images/I/61QGn-0tnwL._SL1500_.jpg",
    "https://m.media-amazon.com/images/I/61QJTTQAgvL._SL1500_.jpg",
    "https://m.media-amazon.com/images/I/61GaDs8b6KL._SL1500_.jpg",
    "https://m.media-amazon.com/images/I/61lKlEtZ3LL._SL1500_.jpg",
    "https://m.media-amazon.com/images/I/61HSk9ZrU2L._SL1500_.jpg",
    "https://m.media-amazon.com/images/I/61I-Tc4UCDL._SL1500_.jpg",
    "https://m.media-amazon.com/images/I/61aiqXM5k4L._SL1500_.jpg",
    "https://m.media-amazon.com/images/I/61Mj+CoKKPL._SL1500_.jpg",
    "https://m.media-amazon.com/images/I/61WV2Ip6akL._SL1500_.jpg",
    "https://m.media-amazon.com/images/I/61-4eMmTZsL._SL1500_.jpg",
    "https://m.media-amazon.com/images/I/61IA-2n5zQL._SL1500_.jpg",
    "https://m.media-amazon.com/images/I/61bP-Ry4zZL._SL1500_.jpg",
    "https://m.media-amazon.com/images/I/613Nhkdpa2L._SL1500_.jpg",
    "https://m.media-amazon.com/images/I/61vZeUkHXYL._SL1500_.jpg",
    "https://m.media-amazon.com/images/I/61gj7qN4mwL._SL1500_.jpg",
    "https://m.media-amazon.com/images/I/61N9kbKfimL._SL1500_.jpg",
    "https://m.media-amazon.com/images/I/61EuYZGIQ-L._SL1500_.jpg",
    "https://m.media-amazon.com/images/I/610eC28WaJL._SL1500_.jpg",
    "https://m.media-amazon.com/images/I/612OoGoDpHL._SL1500_.jpg",
    "https://m.media-amazon.com/images/I/6179heyHIkL._SL1500_.jpg",
    "https://m.media-amazon.com/images/I/610UGvtYEHL._SL1500_.jpg",
    "https://m.media-amazon.com/images/I/61yWE+XXB7L._SL1500_.jpg",
    "https://m.media-amazon.com/images/I/61mTF+SDlzL._SL1500_.jpg",
    "https://m.media-amazon.com/images/I/61fODjC-EbL._SL1500_.jpg",
    "https://m.media-amazon.com/images/I/614I-TNFEAL._SL1500_.jpg",
    "https://m.media-amazon.com/images/I/61QAsKSi0hL._SL1500_.jpg",
    "https://m.media-amazon.com/images/I/61bHWmOFpeL._SL1500_.jpg",
    "https://m.media-amazon.com/images/I/61aLkX+06uL._SL1500_.jpg",
    "https://m.media-amazon.com/images/I/61yOCENU1gL._SL1500_.jpg"
  ],
  "gallery_images": [
    "https://m.media-amazon.com/images/I/61ODaWZ8uJL._SL1500_.jpg",
    "https://m.media-amazon.com/images/I/71HTV7xAsqL._SL1500_.jpg",
    "https://m.media-amazon.com/images/I/714AFJ345mL._SL1500_.jpg",
    "https://m.media-amazon.com/images/I/71slq7f5seL._SL1500_.jpg",
    "https://m.media-amazon.com/images/I/71SkpMs8AjL._SL1500_.jpg",
    "https://m.media-amazon.com/images/I/71M9cVP3BDL._SL1500_.jpg",
    "https://m.media-amazon.com/images/I/7111QzGravL._SL1500_.jpg",
    "https://m.media-amazon.com/images/I/61h1AhS4CNL._SL1500_.jpg",
    "https://m.media-amazon.com/images/I/61LXS2IeA0L._SL1500_.jpg",
    "https://m.media-amazon.com/images/I/615X6SlFD-L._SL1500_.jpg",
    "https://m.media-amazon.com/images/I/61QGn-0tnwL._SL1500_.jpg",
    "https://m.media-amazon.com/images/I/61QJTTQAgvL._SL1500_.jpg",
    "https://m.media-amazon.com/images/I/61GaDs8b6KL._SL1500_.jpg",
    "https://m.media-amazon.com/images/I/61lKlEtZ3LL._SL1500_.jpg",
    "https://m.media-amazon.com/images/I/61HSk9ZrU2L._SL1500_.jpg",
    "https://m.media-amazon.com/images/I/61I-Tc4UCDL._SL1500_.jpg",
    "https://m.media-amazon.com/images/I/61aiqXM5k4L._SL1500_.jpg",
    "https://m.media-amazon.com/images/I/61Mj+CoKKPL._SL1500_.jpg",
    "https://m.media-amazon.com/images/I/61WV2Ip6akL._SL1500_.jpg",
    "https://m.media-amazon.com/images/I/61-4eMmTZsL._SL1500_.jpg",
    "https://m.media-amazon.com/images/I/61IA-2n5zQL._SL1500_.jpg",
    "https://m.media-amazon.com/images/I/61bP-Ry4zZL._SL1500_.jpg",
    "https://m.media-amazon.com/images/I/613Nhkdpa2L._SL1500_.jpg",
    "https://m.media-amazon.com/images/I/61vZeUkHXYL._SL1500_.jpg",
    "https://m.media-amazon.com/images/I/61gj7qN4mwL._SL1500_.jpg",
    "https://m.media-amazon.com/images/I/61N9kbKfimL._SL1500_.jpg",
    "https://m.media-amazon.com/images/I/61EuYZGIQ-L._SL1500_.jpg",
    "https://m.media-amazon.com/images/I/610eC28WaJL._SL1500_.jpg",
    "https://m.media-amazon.com/images/I/612OoGoDpHL._SL1500_.jpg",
    "https://m.media-amazon.com/images/I/6179heyHIkL._SL1500_.jpg",
    "https://m.media-amazon.com/images/I/610UGvtYEHL._SL1500_.jpg",
    "https://m.media-amazon.com/images/I/61yWE+XXB7L._SL1500_.jpg",
    "https://m.media-amazon.com/images/I/61mTF+SDlzL._SL1500_.jpg",
    "https://m.media-amazon.com/images/I/61fODjC-EbL._SL1500_.jpg",
    "https://m.media-amazon.com/images/I/614I-TNFEAL._SL1500_.jpg",
    "https://m.media-amazon.com/images/I/61QAsKSi0hL._SL1500_.jpg",
    "https://m.media-amazon.com/images/I/61bHWmOFpeL._SL1500_.jpg",
    "https://m.media-amazon.com/images/I/61aLkX+06uL._SL1500_.jpg",
    "https://m.media-amazon.com/images/I/61yOCENU1gL._SL1500_.jpg"
  ],
  "aplus_images": [],
  "description_images": [],
  "bullets": [],
  "specs": {
    "Item model number ‏": "‎ HX005",
    "Department ‏": "‎ womens",
    "Date First Available ‏": "‎ December 11, 2025",
    "Manufacturer ‏": "‎ Skbue",
    "ASIN ‏": "‎ B0G6DNPBGL"
  },
  "category": "Clothing, Shoes & Jewelry > Women > Clothing > Dresses > Formal",
  "variations": {
    "sizes": [
      "5",
      "5.5",
      "6",
      "6.5",
      "7",
      "7.5",
      "8",
      "8.5",
      "9",
      "9.5",
      "10",
      "11"
    ],
    "colors": [
      "Fuchsia",
      "Black",
      "Champagne",
      "Dusty Blue",
      "Orange",
      "Peacock",
      "Plum",
      "Blush Pink",
      "Lavender",
      "Royal Blue",
      "Teal",
      "Wisteria",
      "Turquoise",
      "Grey",
      "Gold",
      "Maroon",
      "Blue",
      "Burgundy",
      "Burnt Orange",
      "Rose Gold",
      "Hot Pink",
      "Navy Blue",
      "Dusty Rose",
      "Light Blue",
      "Mint Green",
      "Red",
      "Taupe",
      "Lilac",
      "Silver",
      "White",
      "Ivory",
      "Purple",
      "Yellow",
      "Emerald Green"
    ],
    "size_chart": null
  },
  "reviews": {
    "average_rating": 4.0,
    "count": 0,
    "customers_say": null,
    "items": []
  },
  "short_description": "Womens Maxi Dress Mermaid Short Sleeve Formal is made for a polished look that still feels comfortable to wear. It is designed to sit cleanly on the body with a flattering shape that works for day plans and dressier moments without feeling overdone.\n\nThe fit focuses on balance rather than extremes, so you can move naturally while still getting a defined silhouette. Choose your usual size for a closer look, or size up if you prefer a little more ease through the waist and hips.\n\nStyling is simple: keep accessories minimal for a clean finish, or add a jacket and statement shoes when you want a sharper outfit. This piece photographs well thanks to smooth lines and a structured feel that stays put once you have it adjusted.\n\nWith the right fit and simple styling, this item becomes an easy go-to when you want something that looks intentional without requiring extra effort.\n\nThe design is easy to style with simple accessories and works well in photos thanks to clean lines and a balanced silhouette.\n\nIf you are between sizes, choose based on how close you like the fit through the waist and hips, then adjust with your usual layering choices.",
  "about_this_item": "Womens Maxi Dress Mermaid Short Sleeve Formal is made for a polished look that still feels comfortable to wear. It is designed to sit cleanly on the body with a flattering shape that works for day plans and dressier moments without feeling overdone.\n\nThe fit focuses on balance rather than extremes, so you can move naturally while still getting a defined silhouette. Choose your usual size for a closer look, or size up if you prefer a little more ease through the waist and hips.\n\nStyling is simple: keep accessories minimal for a clean finish, or add a jacket and statement shoes when you want a sharper outfit. This piece photographs well thanks to smooth lines and a structured feel that stays put once you have it adjusted.\n\nWith the right fit and simple styling, this item becomes an easy go-to when you want something that looks intentional without requiring extra effort.\n\nThe design is easy to style with simple accessories and works well in photos thanks to clean lines and a balanced silhouette.\n\nIf you are between sizes, choose based on how close you like the fit through the waist and hips, then adjust with your usual layering choices.",
  "long_description": "Womens Maxi Dress Mermaid Short Sleeve Formal is a versatile piece you can reach for when you want a put-together look that still feels comfortable. The goal is simple: a silhouette that reads polished, photographs well, and stays wearable for a full day or a long night.\n\nFit and sizing Fit is where most outfits win or lose. This design aims for a balanced shape with a defined line through the torso, a clean waist, and a smooth finish through the hips and legs. If you prefer a more relaxed feel, size up; if you like a closer fit, stay true to size. Sizes may include: 5, 5.5, 6, 6.5, 7, 7.5, 8, 8.5, 9, 9.5, 10, 11.\n\nFabric and comfort Comfort is not just about softness. It is also about movement and how the fabric behaves as you walk, sit, and stand. A fabric blend with a bit of give helps it keep its shape while still feeling wearable.\n\nHighlights A clean neckline and a refined silhouette for an elevated look. Designed to layer easily with jackets, wraps, or sweaters. Works well with both minimal accessories and statement pieces.\n\nHow to style Styling ideas: keep it minimal with neutral shoes and one standout accessory. For a relaxed daytime look, add a denim jacket or cardigan. For events, switch to a bolder shoe and a small clutch for a sharper finish.\n\nColor notes Available colors may include: Fuchsia, Black, Champagne, Dusty Blue, Orange, Peacock, Plum, Blush Pink, Lavender, Royal Blue, Teal, Wisteria, Turquoise, Grey. If a shade is sold out, check back as availability can change.\n\nCare Care guidance matters if you want it to keep its shape and finish. Follow the label first.",
  "long_description_blocks": [
    {
      "type": "p",
      "text": "Womens Maxi Dress Mermaid Short Sleeve Formal is a versatile piece you can reach for when you want a put-together look that still feels comfortable. The goal is simple: a silhouette that reads polished, photographs well, and stays wearable for a full day or a long night."
    },
    {
      "type": "p",
      "text": "Fit and sizing Fit is where most outfits win or lose. This design aims for a balanced shape with a defined line through the torso, a clean waist, and a smooth finish through the hips and legs. If you prefer a more relaxed feel, size up; if you like a closer fit, stay true to size. Sizes may include: 5, 5.5, 6, 6.5, 7, 7.5, 8, 8.5, 9, 9.5, 10, 11."
    },
    {
      "type": "p",
      "text": "Fabric and comfort Comfort is not just about softness. It is also about movement and how the fabric behaves as you walk, sit, and stand. A fabric blend with a bit of give helps it keep its shape while still feeling wearable."
    },
    {
      "type": "p",
      "text": "Highlights A clean neckline and a refined silhouette for an elevated look. Designed to layer easily with jackets, wraps, or sweaters. Works well with both minimal accessories and statement pieces."
    },
    {
      "type": "p",
      "text": "How to style Styling ideas: keep it minimal with neutral shoes and one standout accessory. For a relaxed daytime look, add a denim jacket or cardigan. For events, switch to a bolder shoe and a small clutch for a sharper finish."
    },
    {
      "type": "p",
      "text": "Color notes Available colors may include: Fuchsia, Black, Champagne, Dusty Blue, Orange, Peacock, Plum, Blush Pink, Lavender, Royal Blue, Teal, Wisteria, Turquoise, Grey. If a shade is sold out, check back as availability can change."
    },
    {
      "type": "p",
      "text": "Care Care guidance matters if you want it to keep its shape and finish. Follow the label first."
    }
  ],
  "videos": [
    {
      "id": "09d47b88-9182-4ec9-97eb-6b61b22beef0",
      "src": "https://m.media-amazon.com/images/S/vse-vms-transcoding-artifact-us-east-1-prod/09d47b88-9182-4ec9-97eb-6b61b22beef0/default.jobtemplate.hls.m3u8",
      "sources": [
        {
          "type": "application/x-mpegURL",
          "src": "https://m.media-amazon.com/images/S/vse-vms-transcoding-artifact-us-east-1-prod/09d47b88-9182-4ec9-97eb-6b61b22beef0/default.jobtemplate.hls.m3u8"
        }
      ]
    },
    {
      "id": "b3ce89eb-5c16-4eb0-9459-520800fa33d1",
      "src": "https://m.media-amazon.com/images/S/vse-vms-transcoding-artifact-us-east-1-prod/b3ce89eb-5c16-4eb0-9459-520800fa33d1/videopreview.jobtemplate.mp4.default.mp4",
      "sources": [
        {
          "type": "video/mp4",
          "src": "https://m.media-amazon.com/images/S/vse-vms-transcoding-artifact-us-east-1-prod/b3ce89eb-5c16-4eb0-9459-520800fa33d1/videopreview.jobtemplate.mp4.default.mp4"
        }
      ]
    }
  ],
  "color_swatches": {
    "Fuchsia": "https://m.media-amazon.com/images/I/31jf7g0ZXML._AC_SR38,50_.jpg",
    "Black": "https://m.media-amazon.com/images/I/31VXHBj3gML._AC_SR38,50_.jpg",
    "Champagne": "https://m.media-amazon.com/images/I/31hsu3ZyHML._AC_SR38,50_.jpg",
    "Dusty Blue": "https://m.media-amazon.com/images/I/31AunPfeR9L._AC_SR38,50_.jpg",
    "Orange": "https://m.media-amazon.com/images/I/31sypLzk1EL._AC_SR38,50_.jpg",
    "Peacock": "https://m.media-amazon.com/images/I/31Gc5l6eGPL._AC_SR38,50_.jpg",
    "Plum": "https://m.media-amazon.com/images/I/31iWEIELljL._AC_SR38,50_.jpg",
    "Blush Pink": "https://m.media-amazon.com/images/I/31lE5Qdr8oL._AC_SR38,50_.jpg",
    "Lavender": "https://m.media-amazon.com/images/I/315UE9rr4aL._AC_SR38,50_.jpg",
    "Royal Blue": "https://m.media-amazon.com/images/I/31ZvbjCUJJL._AC_SR38,50_.jpg",
    "Teal": "https://m.media-amazon.com/images/I/31zRtJeTq-L._AC_SR38,50_.jpg",
    "Wisteria": "https://m.media-amazon.com/images/I/31eC62CyedL._AC_SR38,50_.jpg",
    "Turquoise": "https://m.media-amazon.com/images/I/31DnJHmjaXL._AC_SR38,50_.jpg",
    "Grey": "https://m.media-amazon.com/images/I/31VsRBZknoL._AC_SR38,50_.jpg",
    "Gold": "https://m.media-amazon.com/images/I/31JieI6MeIL._AC_SR38,50_.jpg",
    "Maroon": "https://m.media-amazon.com/images/I/31imW19MHUL._AC_SR38,50_.jpg",
    "Blue": "https://m.media-amazon.com/images/I/31FGls9ZUUL._AC_SR38,50_.jpg",
    "Burgundy": "https://m.media-amazon.com/images/I/31hm4BO6EnL._AC_SR38,50_.jpg",
    "Burnt Orange": "https://m.media-amazon.com/images/I/31sypLzk1EL._AC_SR38,50_.jpg",
    "Rose Gold": "https://m.media-amazon.com/images/I/31zNzsezktL._AC_SR38,50_.jpg",
    "Hot Pink": "https://m.media-amazon.com/images/I/31m69QZroAL._AC_SR38,50_.jpg",
    "Navy Blue": "https://m.media-amazon.com/images/I/31N9JUGPueL._AC_SR38,50_.jpg",
    "Dusty Rose": "https://m.media-amazon.com/images/I/31PkKCI93nL._AC_SR38,50_.jpg",
    "Light Blue": "https://m.media-amazon.com/images/I/31XxESfQjzL._AC_SR38,50_.jpg",
    "Mint Green": "https://m.media-amazon.com/images/I/31RKxaO1riL._AC_SR38,50_.jpg",
    "Red": "https://m.media-amazon.com/images/I/312IrAna0RL._AC_SR38,50_.jpg",
    "Taupe": "https://m.media-amazon.com/images/I/31sgVdaOA0L._AC_SR38,50_.jpg",
    "Lilac": "https://m.media-amazon.com/images/I/31hhcsoBFRL._AC_SR38,50_.jpg",
    "Silver": "https://m.media-amazon.com/images/I/31t-ISWvoPL._AC_SR38,50_.jpg",
    "White": "https://m.media-amazon.com/images/I/31kWj8C76zL._AC_SR38,50_.jpg",
    "Ivory": "https://m.media-amazon.com/images/I/31pGdwLiOML._AC_SR38,50_.jpg",
    "Purple": "https://m.media-amazon.com/images/I/31-hw0MPuSL._AC_SR38,50_.jpg",
    "Yellow": "https://m.media-amazon.com/images/I/31WQb57+eNL._AC_SR38,50_.jpg",
    "Emerald Green": "https://m.media-amazon.com/images/I/31lRUoXtpML._AC_SR38,50_.jpg"
  },
  "color_image_key": {
    "Fuchsia": "61h1AhS4CNL",
    "Black": "61LXS2IeA0L",
    "Champagne": "61ODaWZ8uJL",
    "Dusty Blue": "615X6SlFD-L",
    "Orange": "61QGn-0tnwL",
    "Peacock": "61QJTTQAgvL",
    "Plum": "61GaDs8b6KL",
    "Blush Pink": "61lKlEtZ3LL",
    "Lavender": "61HSk9ZrU2L",
    "Royal Blue": "61I-Tc4UCDL",
    "Teal": "61aiqXM5k4L",
    "Wisteria": "61Mj+CoKKPL",
    "Turquoise": "61WV2Ip6akL",
    "Grey": "61-4eMmTZsL",
    "Gold": "61IA-2n5zQL",
    "Maroon": "61bP-Ry4zZL",
    "Blue": "613Nhkdpa2L",
    "Burgundy": "61vZeUkHXYL",
    "Burnt Orange": "61QGn-0tnwL",
    "Rose Gold": "61gj7qN4mwL",
    "Hot Pink": "61N9kbKfimL",
    "Navy Blue": "61EuYZGIQ-L",
    "Dusty Rose": "610eC28WaJL",
    "Light Blue": "612OoGoDpHL",
    "Mint Green": "6179heyHIkL",
    "Red": "610UGvtYEHL",
    "Taupe": "61yWE+XXB7L",
    "Lilac": "61mTF+SDlzL",
    "Silver": "61fODjC-EbL",
    "White": "614I-TNFEAL",
    "Ivory": "61QAsKSi0hL",
    "Purple": "61bHWmOFpeL",
    "Yellow": "61aLkX+06uL",
    "Emerald Green": "61yOCENU1gL"
  },
  "color_images": {
    "Fuchsia": [
      "https://m.media-amazon.com/images/I/61h1AhS4CNL._SL1500_.jpg",
      "https://m.media-amazon.com/images/I/71HTV7xAsqL._SL1500_.jpg",
      "https://m.media-amazon.com/images/I/714AFJ345mL._SL1500_.jpg",
      "https://m.media-amazon.com/images/I/71slq7f5seL._SL1500_.jpg",
      "https://m.media-amazon.com/images/I/71SkpMs8AjL._SL1500_.jpg",
      "https://m.media-amazon.com/images/I/71M9cVP3BDL._SL1500_.jpg",
      "https://m.media-amazon.com/images/I/7111QzGravL._SL1500_.jpg"
    ],
    "Black": [
      "https://m.media-amazon.com/images/I/61LXS2IeA0L._SL1500_.jpg",
      "https://m.media-amazon.com/images/I/71HTV7xAsqL._SL1500_.jpg",
      "https://m.media-amazon.com/images/I/714AFJ345mL._SL1500_.jpg",
      "https://m.media-amazon.com/images/I/71slq7f5seL._SL1500_.jpg",
      "https://m.media-amazon.com/images/I/71SkpMs8AjL._SL1500_.jpg",
      "https://m.media-amazon.com/images/I/71M9cVP3BDL._SL1500_.jpg",
      "https://m.media-amazon.com/images/I/7111QzGravL._SL1500_.jpg"
    ],
    "Champagne": [
      "https://m.media-amazon.com/images/I/61ODaWZ8uJL._SL1500_.jpg",
      "https://m.media-amazon.com/images/I/71HTV7xAsqL._SL1500_.jpg",
      "https://m.media-amazon.com/images/I/714AFJ345mL._SL1500_.jpg",
      "https://m.media-amazon.com/images/I/71slq7f5seL._SL1500_.jpg",
      "https://m.media-amazon.com/images/I/71SkpMs8AjL._SL1500_.jpg",
      "https://m.media-amazon.com/images/I/71M9cVP3BDL._SL1500_.jpg",
      "https://m.media-amazon.com/images/I/7111QzGravL._SL1500_.jpg"
    ],
    "Dusty Blue": [
      "https://m.media-amazon.com/images/I/615X6SlFD-L._SL1500_.jpg",
      "https://m.media-amazon.com/images/I/71HTV7xAsqL._SL1500_.jpg",
      "https://m.media-amazon.com/images/I/714AFJ345mL._SL1500_.jpg",
      "https://m.media-amazon.com/images/I/71slq7f5seL._SL1500_.jpg",
      "https://m.media-amazon.com/images/I/71SkpMs8AjL._SL1500_.jpg",
      "https://m.media-amazon.com/images/I/71M9cVP3BDL._SL1500_.jpg",
      "https://m.media-amazon.com/images/I/7111QzGravL._SL1500_.jpg"
    ],
    "Orange": [
      "https://m.media-amazon.com/images/I/61QGn-0tnwL._SL1500_.jpg",
      "https://m.media-amazon.com/images/I/71HTV7xAsqL._SL1500_.jpg",
      "https://m.media-amazon.com/images/I/714AFJ345mL._SL1500_.jpg",
      "https://m.media-amazon.com/images/I/71slq7f5seL._SL1500_.jpg",
      "https://m.media-amazon.com/images/I/71SkpMs8AjL._SL1500_.jpg",
      "https://m.media-amazon.com/images/I/71M9cVP3BDL._SL1500_.jpg",
      "https://m.media-amazon.com/images/I/7111QzGravL._SL1500_.jpg"
    ],
    "Peacock": [
      "https://m.media-amazon.com/images/I/61QJTTQAgvL._SL1500_.jpg",
      "https://m.media-amazon.com/images/I/71HTV7xAsqL._SL1500_.jpg",
      "https://m.media-amazon.com/images/I/714AFJ345mL._SL1500_.jpg",
      "https://m.media-amazon.com/images/I/71slq7f5seL._SL1500_.jpg",
      "https://m.media-amazon.com/images/I/71SkpMs8AjL._SL1500_.jpg",
      "https://m.media-amazon.com/images/I/71M9cVP3BDL._SL1500_.jpg",
      "https://m.media-amazon.com/images/I/7111QzGravL._SL1500_.jpg"
    ],
    "Plum": [
      "https://m.media-amazon.com/images/I/61GaDs8b6KL._SL1500_.jpg",
      "https://m.media-amazon.com/images/I/71HTV7xAsqL._SL1500_.jpg",
      "https://m.media-amazon.com/images/I/714AFJ345mL._SL1500_.jpg",
      "https://m.media-amazon.com/images/I/71slq7f5seL._SL1500_.jpg",
      "https://m.media-amazon.com/images/I/71SkpMs8AjL._SL1500_.jpg",
      "https://m.media-amazon.com/images/I/71M9cVP3BDL._SL1500_.jpg",
      "https://m.media-amazon.com/images/I/7111QzGravL._SL1500_.jpg"
    ],
    "Blush Pink": [
      "https://m.media-amazon.com/images/I/61lKlEtZ3LL._SL1500_.jpg",
      "https://m.media-amazon.com/images/I/71HTV7xAsqL._SL1500_.jpg",
      "https://m.media-amazon.com/images/I/714AFJ345mL._SL1500_.jpg",
      "https://m.media-amazon.com/images/I/71slq7f5seL._SL1500_.jpg",
      "https://m.media-amazon.com/images/I/71SkpMs8AjL._SL1500_.jpg",
      "https://m.media-amazon.com/images/I/71M9cVP3BDL._SL1500_.jpg",
      "https://m.media-amazon.com/images/I/7111QzGravL._SL1500_.jpg"
    ],
    "Lavender": [
      "https://m.media-amazon.com/images/I/61HSk9ZrU2L._SL1500_.jpg",
      "https://m.media-amazon.com/images/I/71HTV7xAsqL._SL1500_.jpg",
      "https://m.media-amazon.com/images/I/714AFJ345mL._SL1500_.jpg",
      "https://m.media-amazon.com/images/I/71slq7f5seL._SL1500_.jpg",
      "https://m.media-amazon.com/images/I/71SkpMs8AjL._SL1500_.jpg",
      "https://m.media-amazon.com/images/I/71M9cVP3BDL._SL1500_.jpg",
      "https://m.media-amazon.com/images/I/7111QzGravL._SL1500_.jpg"
    ],
    "Royal Blue": [
      "https://m.media-amazon.com/images/I/61I-Tc4UCDL._SL1500_.jpg",
      "https://m.media-amazon.com/images/I/71HTV7xAsqL._SL1500_.jpg",
      "https://m.media-amazon.com/images/I/714AFJ345mL._SL1500_.jpg",
      "https://m.media-amazon.com/images/I/71slq7f5seL._SL1500_.jpg",
      "https://m.media-amazon.com/images/I/71SkpMs8AjL._SL1500_.jpg",
      "https://m.media-amazon.com/images/I/71M9cVP3BDL._SL1500_.jpg",
      "https://m.media-amazon.com/images/I/7111QzGravL._SL1500_.jpg"
    ],
    "Teal": [
      "https://m.media-amazon.com/images/I/61aiqXM5k4L._SL1500_.jpg",
      "https://m.media-amazon.com/images/I/71HTV7xAsqL._SL1500_.jpg",
      "https://m.media-amazon.com/images/I/714AFJ345mL._SL1500_.jpg",
      "https://m.media-amazon.com/images/I/71slq7f5seL._SL1500_.jpg",
      "https://m.media-amazon.com/images/I/71SkpMs8AjL._SL1500_.jpg",
      "https://m.media-amazon.com/images/I/71M9cVP3BDL._SL1500_.jpg",
      "https://m.media-amazon.com/images/I/7111QzGravL._SL1500_.jpg"
    ],
    "Wisteria": [
      "https://m.media-amazon.com/images/I/61Mj+CoKKPL._SL1500_.jpg",
      "https://m.media-amazon.com/images/I/71HTV7xAsqL._SL1500_.jpg",
      "https://m.media-amazon.com/images/I/714AFJ345mL._SL1500_.jpg",
      "https://m.media-amazon.com/images/I/71slq7f5seL._SL1500_.jpg",
      "https://m.media-amazon.com/images/I/71SkpMs8AjL._SL1500_.jpg",
      "https://m.media-amazon.com/images/I/71M9cVP3BDL._SL1500_.jpg",
      "https://m.media-amazon.com/images/I/7111QzGravL._SL1500_.jpg"
    ],
    "Turquoise": [
      "https://m.media-amazon.com/images/I/61WV2Ip6akL._SL1500_.jpg",
      "https://m.media-amazon.com/images/I/71HTV7xAsqL._SL1500_.jpg",
      "https://m.media-amazon.com/images/I/714AFJ345mL._SL1500_.jpg",
      "https://m.media-amazon.com/images/I/71slq7f5seL._SL1500_.jpg",
      "https://m.media-amazon.com/images/I/71SkpMs8AjL._SL1500_.jpg",
      "https://m.media-amazon.com/images/I/71M9cVP3BDL._SL1500_.jpg",
      "https://m.media-amazon.com/images/I/7111QzGravL._SL1500_.jpg"
    ],
    "Grey": [
      "https://m.media-amazon.com/images/I/61-4eMmTZsL._SL1500_.jpg",
      "https://m.media-amazon.com/images/I/71HTV7xAsqL._SL1500_.jpg",
      "https://m.media-amazon.com/images/I/714AFJ345mL._SL1500_.jpg",
      "https://m.media-amazon.com/images/I/71slq7f5seL._SL1500_.jpg",
      "https://m.media-amazon.com/images/I/71SkpMs8AjL._SL1500_.jpg",
      "https://m.media-amazon.com/images/I/71M9cVP3BDL._SL1500_.jpg",
      "https://m.media-amazon.com/images/I/7111QzGravL._SL1500_.jpg"
    ],
    "Gold": [
      "https://m.media-amazon.com/images/I/61IA-2n5zQL._SL1500_.jpg",
      "https://m.media-amazon.com/images/I/71HTV7xAsqL._SL1500_.jpg",
      "https://m.media-amazon.com/images/I/714AFJ345mL._SL1500_.jpg",
      "https://m.media-amazon.com/images/I/71slq7f5seL._SL1500_.jpg",
      "https://m.media-amazon.com/images/I/71SkpMs8AjL._SL1500_.jpg",
      "https://m.media-amazon.com/images/I/71M9cVP3BDL._SL1500_.jpg",
      "https://m.media-amazon.com/images/I/7111QzGravL._SL1500_.jpg"
    ],
    "Maroon": [
      "https://m.media-amazon.com/images/I/61bP-Ry4zZL._SL1500_.jpg",
      "https://m.media-amazon.com/images/I/71HTV7xAsqL._SL1500_.jpg",
      "https://m.media-amazon.com/images/I/714AFJ345mL._SL1500_.jpg",
      "https://m.media-amazon.com/images/I/71slq7f5seL._SL1500_.jpg",
      "https://m.media-amazon.com/images/I/71SkpMs8AjL._SL1500_.jpg",
      "https://m.media-amazon.com/images/I/71M9cVP3BDL._SL1500_.jpg",
      "https://m.media-amazon.com/images/I/7111QzGravL._SL1500_.jpg"
    ],
    "Blue": [
      "https://m.media-amazon.com/images/I/613Nhkdpa2L._SL1500_.jpg",
      "https://m.media-amazon.com/images/I/71HTV7xAsqL._SL1500_.jpg",
      "https://m.media-amazon.com/images/I/714AFJ345mL._SL1500_.jpg",
      "https://m.media-amazon.com/images/I/71slq7f5seL._SL1500_.jpg",
      "https://m.media-amazon.com/images/I/71SkpMs8AjL._SL1500_.jpg",
      "https://m.media-amazon.com/images/I/71M9cVP3BDL._SL1500_.jpg",
      "https://m.media-amazon.com/images/I/7111QzGravL._SL1500_.jpg"
    ],
    "Burgundy": [
      "https://m.media-amazon.com/images/I/61vZeUkHXYL._SL1500_.jpg",
      "https://m.media-amazon.com/images/I/71HTV7xAsqL._SL1500_.jpg",
      "https://m.media-amazon.com/images/I/714AFJ345mL._SL1500_.jpg",
      "https://m.media-amazon.com/images/I/71slq7f5seL._SL1500_.jpg",
      "https://m.media-amazon.com/images/I/71SkpMs8AjL._SL1500_.jpg",
      "https://m.media-amazon.com/images/I/71M9cVP3BDL._SL1500_.jpg",
      "https://m.media-amazon.com/images/I/7111QzGravL._SL1500_.jpg"
    ],
    "Burnt Orange": [
      "https://m.media-amazon.com/images/I/61QGn-0tnwL._SL1500_.jpg",
      "https://m.media-amazon.com/images/I/71HTV7xAsqL._SL1500_.jpg",
      "https://m.media-amazon.com/images/I/714AFJ345mL._SL1500_.jpg",
      "https://m.media-amazon.com/images/I/71slq7f5seL._SL1500_.jpg",
      "https://m.media-amazon.com/images/I/71SkpMs8AjL._SL1500_.jpg",
      "https://m.media-amazon.com/images/I/71M9cVP3BDL._SL1500_.jpg",
      "https://m.media-amazon.com/images/I/7111QzGravL._SL1500_.jpg"
    ],
    "Rose Gold": [
      "https://m.media-amazon.com/images/I/61gj7qN4mwL._SL1500_.jpg",
      "https://m.media-amazon.com/images/I/71HTV7xAsqL._SL1500_.jpg",
      "https://m.media-amazon.com/images/I/714AFJ345mL._SL1500_.jpg",
      "https://m.media-amazon.com/images/I/71slq7f5seL._SL1500_.jpg",
      "https://m.media-amazon.com/images/I/71SkpMs8AjL._SL1500_.jpg",
      "https://m.media-amazon.com/images/I/71M9cVP3BDL._SL1500_.jpg",
      "https://m.media-amazon.com/images/I/7111QzGravL._SL1500_.jpg"
    ],
    "Hot Pink": [
      "https://m.media-amazon.com/images/I/61N9kbKfimL._SL1500_.jpg",
      "https://m.media-amazon.com/images/I/71HTV7xAsqL._SL1500_.jpg",
      "https://m.media-amazon.com/images/I/714AFJ345mL._SL1500_.jpg",
      "https://m.media-amazon.com/images/I/71slq7f5seL._SL1500_.jpg",
      "https://m.media-amazon.com/images/I/71SkpMs8AjL._SL1500_.jpg",
      "https://m.media-amazon.com/images/I/71M9cVP3BDL._SL1500_.jpg",
      "https://m.media-amazon.com/images/I/7111QzGravL._SL1500_.jpg"
    ],
    "Navy Blue": [
      "https://m.media-amazon.com/images/I/61EuYZGIQ-L._SL1500_.jpg",
      "https://m.media-amazon.com/images/I/71HTV7xAsqL._SL1500_.jpg",
      "https://m.media-amazon.com/images/I/714AFJ345mL._SL1500_.jpg",
      "https://m.media-amazon.com/images/I/71slq7f5seL._SL1500_.jpg",
      "https://m.media-amazon.com/images/I/71SkpMs8AjL._SL1500_.jpg",
      "https://m.media-amazon.com/images/I/71M9cVP3BDL._SL1500_.jpg",
      "https://m.media-amazon.com/images/I/7111QzGravL._SL1500_.jpg"
    ],
    "Dusty Rose": [
      "https://m.media-amazon.com/images/I/610eC28WaJL._SL1500_.jpg",
      "https://m.media-amazon.com/images/I/71HTV7xAsqL._SL1500_.jpg",
      "https://m.media-amazon.com/images/I/714AFJ345mL._SL1500_.jpg",
      "https://m.media-amazon.com/images/I/71slq7f5seL._SL1500_.jpg",
      "https://m.media-amazon.com/images/I/71SkpMs8AjL._SL1500_.jpg",
      "https://m.media-amazon.com/images/I/71M9cVP3BDL._SL1500_.jpg",
      "https://m.media-amazon.com/images/I/7111QzGravL._SL1500_.jpg"
    ],
    "Light Blue": [
      "https://m.media-amazon.com/images/I/612OoGoDpHL._SL1500_.jpg",
      "https://m.media-amazon.com/images/I/71HTV7xAsqL._SL1500_.jpg",
      "https://m.media-amazon.com/images/I/714AFJ345mL._SL1500_.jpg",
      "https://m.media-amazon.com/images/I/71slq7f5seL._SL1500_.jpg",
      "https://m.media-amazon.com/images/I/71SkpMs8AjL._SL1500_.jpg",
      "https://m.media-amazon.com/images/I/71M9cVP3BDL._SL1500_.jpg",
      "https://m.media-amazon.com/images/I/7111QzGravL._SL1500_.jpg"
    ],
    "Mint Green": [
      "https://m.media-amazon.com/images/I/6179heyHIkL._SL1500_.jpg",
      "https://m.media-amazon.com/images/I/71HTV7xAsqL._SL1500_.jpg",
      "https://m.media-amazon.com/images/I/714AFJ345mL._SL1500_.jpg",
      "https://m.media-amazon.com/images/I/71slq7f5seL._SL1500_.jpg",
      "https://m.media-amazon.com/images/I/71SkpMs8AjL._SL1500_.jpg",
      "https://m.media-amazon.com/images/I/71M9cVP3BDL._SL1500_.jpg",
      "https://m.media-amazon.com/images/I/7111QzGravL._SL1500_.jpg"
    ],
    "Red": [
      "https://m.media-amazon.com/images/I/610UGvtYEHL._SL1500_.jpg",
      "https://m.media-amazon.com/images/I/71HTV7xAsqL._SL1500_.jpg",
      "https://m.media-amazon.com/images/I/714AFJ345mL._SL1500_.jpg",
      "https://m.media-amazon.com/images/I/71slq7f5seL._SL1500_.jpg",
      "https://m.media-amazon.com/images/I/71SkpMs8AjL._SL1500_.jpg",
      "https://m.media-amazon.com/images/I/71M9cVP3BDL._SL1500_.jpg",
      "https://m.media-amazon.com/images/I/7111QzGravL._SL1500_.jpg"
    ],
    "Taupe": [
      "https://m.media-amazon.com/images/I/61yWE+XXB7L._SL1500_.jpg",
      "https://m.media-amazon.com/images/I/71HTV7xAsqL._SL1500_.jpg",
      "https://m.media-amazon.com/images/I/714AFJ345mL._SL1500_.jpg",
      "https://m.media-amazon.com/images/I/71slq7f5seL._SL1500_.jpg",
      "https://m.media-amazon.com/images/I/71SkpMs8AjL._SL1500_.jpg",
      "https://m.media-amazon.com/images/I/71M9cVP3BDL._SL1500_.jpg",
      "https://m.media-amazon.com/images/I/7111QzGravL._SL1500_.jpg"
    ],
    "Lilac": [
      "https://m.media-amazon.com/images/I/61mTF+SDlzL._SL1500_.jpg",
      "https://m.media-amazon.com/images/I/71HTV7xAsqL._SL1500_.jpg",
      "https://m.media-amazon.com/images/I/714AFJ345mL._SL1500_.jpg",
      "https://m.media-amazon.com/images/I/71slq7f5seL._SL1500_.jpg",
      "https://m.media-amazon.com/images/I/71SkpMs8AjL._SL1500_.jpg",
      "https://m.media-amazon.com/images/I/71M9cVP3BDL._SL1500_.jpg",
      "https://m.media-amazon.com/images/I/7111QzGravL._SL1500_.jpg"
    ],
    "Silver": [
      "https://m.media-amazon.com/images/I/61fODjC-EbL._SL1500_.jpg",
      "https://m.media-amazon.com/images/I/71HTV7xAsqL._SL1500_.jpg",
      "https://m.media-amazon.com/images/I/714AFJ345mL._SL1500_.jpg",
      "https://m.media-amazon.com/images/I/71slq7f5seL._SL1500_.jpg",
      "https://m.media-amazon.com/images/I/71SkpMs8AjL._SL1500_.jpg",
      "https://m.media-amazon.com/images/I/71M9cVP3BDL._SL1500_.jpg",
      "https://m.media-amazon.com/images/I/7111QzGravL._SL1500_.jpg"
    ],
    "White": [
      "https://m.media-amazon.com/images/I/614I-TNFEAL._SL1500_.jpg",
      "https://m.media-amazon.com/images/I/71HTV7xAsqL._SL1500_.jpg",
      "https://m.media-amazon.com/images/I/714AFJ345mL._SL1500_.jpg",
      "https://m.media-amazon.com/images/I/71slq7f5seL._SL1500_.jpg",
      "https://m.media-amazon.com/images/I/71SkpMs8AjL._SL1500_.jpg",
      "https://m.media-amazon.com/images/I/71M9cVP3BDL._SL1500_.jpg",
      "https://m.media-amazon.com/images/I/7111QzGravL._SL1500_.jpg"
    ],
    "Ivory": [
      "https://m.media-amazon.com/images/I/61QAsKSi0hL._SL1500_.jpg",
      "https://m.media-amazon.com/images/I/71HTV7xAsqL._SL1500_.jpg",
      "https://m.media-amazon.com/images/I/714AFJ345mL._SL1500_.jpg",
      "https://m.media-amazon.com/images/I/71slq7f5seL._SL1500_.jpg",
      "https://m.media-amazon.com/images/I/71SkpMs8AjL._SL1500_.jpg",
      "https://m.media-amazon.com/images/I/71M9cVP3BDL._SL1500_.jpg",
      "https://m.media-amazon.com/images/I/7111QzGravL._SL1500_.jpg"
    ],
    "Purple": [
      "https://m.media-amazon.com/images/I/61bHWmOFpeL._SL1500_.jpg",
      "https://m.media-amazon.com/images/I/71HTV7xAsqL._SL1500_.jpg",
      "https://m.media-amazon.com/images/I/714AFJ345mL._SL1500_.jpg",
      "https://m.media-amazon.com/images/I/71slq7f5seL._SL1500_.jpg",
      "https://m.media-amazon.com/images/I/71SkpMs8AjL._SL1500_.jpg",
      "https://m.media-amazon.com/images/I/71M9cVP3BDL._SL1500_.jpg",
      "https://m.media-amazon.com/images/I/7111QzGravL._SL1500_.jpg"
    ],
    "Yellow": [
      "https://m.media-amazon.com/images/I/61aLkX+06uL._SL1500_.jpg",
      "https://m.media-amazon.com/images/I/71HTV7xAsqL._SL1500_.jpg",
      "https://m.media-amazon.com/images/I/714AFJ345mL._SL1500_.jpg",
      "https://m.media-amazon.com/images/I/71slq7f5seL._SL1500_.jpg",
      "https://m.media-amazon.com/images/I/71SkpMs8AjL._SL1500_.jpg",
      "https://m.media-amazon.com/images/I/71M9cVP3BDL._SL1500_.jpg",
      "https://m.media-amazon.com/images/I/7111QzGravL._SL1500_.jpg"
    ],
    "Emerald Green": [
      "https://m.media-amazon.com/images/I/61yOCENU1gL._SL1500_.jpg",
      "https://m.media-amazon.com/images/I/71HTV7xAsqL._SL1500_.jpg",
      "https://m.media-amazon.com/images/I/714AFJ345mL._SL1500_.jpg",
      "https://m.media-amazon.com/images/I/71slq7f5seL._SL1500_.jpg",
      "https://m.media-amazon.com/images/I/71SkpMs8AjL._SL1500_.jpg",
      "https://m.media-amazon.com/images/I/71M9cVP3BDL._SL1500_.jpg",
      "https://m.media-amazon.com/images/I/7111QzGravL._SL1500_.jpg"
    ]
  },
  "related": [
    {
      "id": "womens-maxi-dress-formal-evening-mermaid",
      "title": "Womens Maxi Dress Formal Evening Mermaid",
      "price": 79.99,
      "category": "Clothing, Shoes & Jewelry > Women > Clothing > Dresses > Formal",
      "images": [
        "https://m.media-amazon.com/images/I/51XOg-esG2L._SL1500_.jpg"
      ]
    },
    {
      "id": "womens-maxi-dress-maxi-evening-formal-cocktail",
      "title": "Womens Maxi Dress Maxi Evening Formal Cocktail",
      "price": 43.31,
      "category": "Clothing, Shoes & Jewelry > Women > Clothing > Dresses > Cocktail",
      "images": [
        "https://m.media-amazon.com/images/I/61xHz823hmL._SL1500_.jpg"
      ]
    },
    {
      "id": "womens-maxi-dress-formal",
      "title": "Womens Maxi Dress Formal",
      "price": 94.99,
      "category": "Clothing, Shoes & Jewelry > Women > Clothing > Dresses > Formal",
      "images": [
        "https://m.media-amazon.com/images/I/71noj3DX6jL._SL1500_.jpg"
      ]
    },
    {
      "id": "womens-dress-bodycon-short-sleeve",
      "title": "Womens Dress Bodycon Short Sleeve",
      "price": 59.99,
      "category": "Clothing, Shoes & Jewelry > Women > Clothing > Dresses > Club & Night Out",
      "images": [
        "https://m.media-amazon.com/images/I/61a6bHOzK-L._SL1500_.jpg"
      ]
    },
    {
      "id": "womens-maxi-dress-maxi",
      "title": "Womens Maxi Dress Maxi",
      "price": 19.99,
      "category": "Clothing, Shoes & Jewelry > Women > Clothing > Dresses > Casual",
      "images": [
        "https://m.media-amazon.com/images/I/71QZPXa-3TL._SL1500_.jpg"
      ]
    }
  ],
  "customer_also_viewed": [
    {
      "id": "womens-maxi-dress-one-shoulder-formal-mermaid-bodycon-evening-maxi",
      "title": "Womens Maxi Dress One Shoulder Formal Mermaid Bodycon Evening Maxi",
      "price": 59.99,
      "category": "Clothing, Shoes & Jewelry > Women > Clothing > Dresses > Club & Night Out",
      "images": [
        "https://m.media-amazon.com/images/I/71mgUBuGwhL._SL1500_.jpg"
      ]
    },
    {
      "id": "womens-maxi-dress-long-sleeve-one-shoulder-formal-bodycon-evening",
      "title": "Womens Maxi Dress Long Sleeve One Shoulder Formal Bodycon Evening",
      "price": 72.99,
      "category": "Clothing, Shoes & Jewelry > Women > Clothing > Dresses > Formal",
      "images": [
        "https://m.media-amazon.com/images/I/61TdBt6xwEL._SL1500_.jpg"
      ]
    },
    {
      "id": "womens-maxi-dress-bodycon-long-sleeve",
      "title": "Womens Maxi Dress Bodycon Long Sleeve",
      "price": 41.99,
      "category": "Clothing, Shoes & Jewelry > Women > Clothing > Dresses > Club & Night Out",
      "images": [
        "https://m.media-amazon.com/images/I/61JaBvecNKL._SL1500_.jpg"
      ]
    },
    {
      "id": "womens-dress-v-neck-cocktail-ruched-sleeveless-bodycon",
      "title": "Womens Dress V Neck Cocktail Ruched Sleeveless Bodycon",
      "price": 47.99,
      "category": "Clothing, Shoes & Jewelry > Women > Clothing > Dresses > Cocktail",
      "images": [
        "https://m.media-amazon.com/images/I/61dlk35b3lL._SL1500_.jpg"
      ]
    },
    {
      "id": "womens-maxi-dress-bodycon-long-sleeve",
      "title": "Womens Maxi Dress Bodycon Long Sleeve",
      "price": 46.98,
      "category": "Clothing, Shoes & Jewelry > Women > Clothing > Dresses > Casual",
      "images": [
        "https://m.media-amazon.com/images/I/61+2KQls6VL._SL1500_.jpg"
      ]
    },
    {
      "id": "womens-maxi-dress-formal-off-shoulder-evening",
      "title": "Womens Maxi Dress Formal Off Shoulder Evening",
      "price": 54.99,
      "category": "Clothing, Shoes & Jewelry > Women > Clothing > Dresses > Formal",
      "images": [
        "https://m.media-amazon.com/images/I/61XzdxMMIDL._SL1500_.jpg"
      ]
    },
    {
      "id": "womens-maxi-dress-cocktail-bodycon-formal-maxi-evening",
      "title": "Womens Maxi Dress Cocktail Bodycon Formal Maxi Evening",
      "price": 109.88,
      "category": "Clothing, Shoes & Jewelry > Women > Clothing > Dresses > Formal",
      "images": [
        "https://m.media-amazon.com/images/I/61PdI3svo0L._SL1500_.jpg"
      ]
    },
    {
      "id": "womens-maxi-dress-long-sleeve-v-neck-bodycon",
      "title": "Womens Maxi Dress Long Sleeve V Neck Bodycon",
      "price": 47.99,
      "category": "Clothing, Shoes & Jewelry > Women > Clothing > Dresses > Casual",
      "images": [
        "https://m.media-amazon.com/images/I/61QbwpUJEwL._SL1500_.jpg"
      ]
    }
  ]
}